Workbook

Sheet Read Me
A1: The Hall of Echoing Mirrors - Economy Model
A2: Does the current design produce runs worth playing? v0.1, greybox.
A4: The question this answers
A5: A run that lasts 8 actions has no queue puzzle, however elegant the overflow rule is.
A6: A run that lasts 800 is a chore. This model finds where the numbers actually land.
A8: Sheets
A9: Parameters Every tunable number. Blue cells are yours; everything else is a formula.
A10: Build Comparison The four archetypes side by side: travel endurance and realm depth.
A11: Run Ledger A step-by-step simulation. Edit the Action and Hue columns to test a route.
A12: Health Checks Pass/fail on the design questions the model exists to answer.
A14: How to use it
A15: 1. Open Health Checks. Anything reading CHECK is a design problem, not a spreadsheet problem.
... A23: Gather has no diminishing returns modelled; set its vitality cost to 0 to see the infinite loop.

Sheet Parameters
A1: Parameters
A2: Blue cells are inputs.
A4: THE CLOCK
A5: Vitality maximum | B5: 100 | C5: The run ends when this hits zero
A6: Overflow multiplier | B6: 1 | C6: Vitality cost per point of unpayable pathos. 1.0 = full price
A8: POOLS
A9: Total pathos budget | B9: 700 | C9: Distributed across 7 pools on Build Comparison
A10: Pool capacity cap per hue | B10: 700 | C10: Ceiling a single pool can hold
A12: ACTION COSTS
A13: Hall traversal - per pool | B13: 15 | C13: Drawn from ALL SEVEN pools. The dominant cost
A14: Realm work - primary hue | B14: 8 | C14: A standard working in the realm's own hue
A15: Realm work - vitality paid | B15: 12 | C15: Burst: pay a working in vitality instead (Maroon)
A16: Gather - yield | B16: 20 | C16: Pathos returned to the target pool
A17: Gather - vitality cost | B17: 2 | C17: Set to 0 to demonstrate the infinite gather loop
A19: TIME
A20: Seconds per action | B20: 4 | C20: Average at 1x speed
A21: Target actions per run - low | B21: 30 | C21: Below this, the queue is too short to be a puzzle
A22: Target actions per run - high | B22: 90 | C22: Above this, planning becomes tedious
A24: WALL THRESHOLDS
A25: Magnitude wall requirement | B25: 400 | C25: Single-hue value needed. Spike territory
A26: Breadth wall requirement | B26: 60 | C26: Needed in 4+ hues AT ONCE. Balanced territory

Sheet Build Comparison
A1: Build Comparison
A2: Allocations are inputs (blue). Everything else is computed. Travel endurance assumes travel-only; realm depth assumes one hue is spent after arriving.
A4: ALLOCATION
A5: Build | B5: Amber | C5: Citrine | D5: Emerald | E5: Sapphire | F5: Iolite | G5: Amethyst | H5: Ruby | I5: Total | J5: Budget OK? | K5: Pays vitality?
A6: Balanced | B6: 100 | C6: 100 | D6: 100 | E6: 100 | F6: 100 | G6: 100 | H6: 100 | I6: =SUM(B6:H6) -> 700 | J6: =IF(I6<=Parameters!$B$9,"OK","OVER BUDGET") -> OK | K6: No
A7: Spike (Ruby) | B7: 10 | C7: 10 | D7: 10 | E7: 10 | F7: 10 | G7: 10 | H7: 640 | I7: =SUM(B7:H7) -> 700 | J7: =IF(I7<=Parameters!$B$9,"OK","OVER BUDGET") -> OK | K7: No
A8: Lopsided | B8: 250 | C8: 200 | D8: 150 | E8: 25 | F8: 25 | G8: 25 | H8: 25 | I8: =SUM(B8:H8) -> 700 | J8: =IF(I8<=Parameters!$B$9,"OK","OVER BUDGET") -> OK | K8: No
A9: Burst | B9: 100 | C9: 100 | D9: 100 | E9: 100 | F9: 100 | G9: 100 | H9: 100 | I9: =SUM(B9:H9) -> 700 | J9: =IF(I9<=Parameters!$B$9,"OK","OVER BUDGET") -> OK | K9: Yes
A12: TRAVEL ENDURANCE
A13: Vitality spent on each successive hall traversal. A pool that runs dry stops absorbing, so its share overflows to vitality.
A14: Build | B14: Trav 1 | C14: Trav 2 | D14: Trav 3 | E14: Trav 4 | F14: Trav 5 | G14: Trav 6 | H14: Trav 7 | I14: Trav 8 | J14: Cum. 1-8 | K14: Max traversals
A15: =A6 -> Balanced | B15: =(MAX(0,Parameters!$B$13-MIN(Parameters!$B$13,MAX(0,B6-Parameters!$B$13*0)))+MAX(0,Parameters!$B$13-MIN(Parameters!$B$13,MAX(0,C6-Parameters!$B$13*0)))+MAX(0,Parameters!$B$13-MIN(Parameters!$B$13,MAX(0,D6-Parameters!$B$13*0)))+MAX(0,Parameters!$B$13-MIN(Parameters!$B$13,MAX(0,E6-Parameters!$B$13*0)))+MAX(0,Parameters!$B$13-MIN(Parameters!$B$13,MAX(0,F6-Parameters!$B$13*0)))+MAX(0,Parameters!$B$13-MIN(Parameters!$B$13,MAX(0,G6-Parameters!$B$13*0)))+MAX(0,Parameters!$B$13-MIN(Parameters!$B$13,MAX(0,H6-Parameters!$B$13*0))))*Parameters!$B$6 -> 0 | C15: =(MAX(0,Parameters!$B$13-MIN(Parameters!$B$13,MAX(0,B6-Parameters!$B$13*1)))+MAX(0,Parameters!$B$13-MIN(Parameters!$B$13,MAX(0,C6-Parameters!$B$13*1)))+MAX(0,Parameters!$B$13-MIN(Parameters!$B$13,MAX(0,D6-Parameters!$B$13*1)))+MAX(0,Parameters!$B$13-MIN(Parameters!$B$13,MAX(0,E6-Parameters!$B$13*1)))+MAX(0,Parameters!$B$13-MIN(Parameters!$B$13,MAX(0,F6-Parameters!$B$13*1)))+MAX(0,Parameters!$B$13-MIN(Parameters!$B$13,MAX(0,G6-Parameters!$B$13*1)))+MAX(0,Parameters!$B$13-MIN(Parameters!$B$13,MAX(0,H6-Parameters!$B$13*1))))*Parameters!$B$6 -> 0 | D15: =(MAX(0,Parameters!$B$13-MIN(Parameters!$B$13,MAX(0,B6-Parameters!$B$13*2)))+MAX(0,Parameters!$B$13-MIN(Parameters!$B$13,MAX(0,C6-Parameters!$B$13*2)))+MAX(0,Parameters!$B$13-MIN(Parameters!$B$13,MAX(0,D6-Parameters!$B$13*2)))+MAX(0,Parameters!$B$13-MIN(Parameters!$B$13,MAX(0,E6-Parameters!$B$13*2)))+MAX(0,Parameters!$B$13-MIN(Parameters!$B$13,MAX(0,F6-Parameters!$B$13*2)))+MAX(0,Parameters!$B$13-MIN(Parameters!$B$13,MAX(0,G6-Parameters!$B$13*2)))+MAX(0,Parameters!$B$13-MIN(Parameters!$B$13,MAX(0,H6-Parameters!$B$13*2))))*Parameters!$B$6 -> 0 | E15: =(MAX(0,Parameters!$B$13-MIN(Parameters!$B$13,MAX(0,B6-Parameters!$B$13*3)))+MAX(0,Parameters!$B$13-MIN(Parameters!$B$13,MAX(0,C6-Parameters!$B$13*3)))+MAX(0,Parameters!$B$13-MIN(Parameters!$B$13,MAX(0,D6-Parameters!$B$13*3)))+MAX(0,Parameters!$B$13-MIN(Parameters!$B$13,MAX(0,E6-Parameters!$B$13*3)))+MAX(0,Parameters!$B$13-MIN(Parameters!$B$13,MAX(0,F6-Parameters!$B$13*3)))+MAX(0,Parameters!$B$13-MIN(Parameters!$B$13,MAX(0,G6-Parameters!$B$13*3)))+MAX(0,Parameters!$B$13-MIN(Parameters!$B$13,MAX(0,H6-Parameters!$B$13*3))))*Parameters!$B$6 -> 0 | F15: =(MAX(0,Parameters!$B$13-MIN(Parameters!$B$13,MAX(0,B6-Parameters!$B$13*4)))+MAX(0,Parameters!$B$13-MIN(Parameters!$B$13,MAX(0,C6-Parameters!$B$13*4)))+MAX(0,Parameters!$B$13-MIN(Parameters!$B$13,MAX(0,D6-Parameters!$B$13*4)))+MAX(0,Parameters!$B$13-MIN(Parameters!$B$13,MAX(0,E6-Parameters!$B$13*4)))+MAX(0,Parameters!$B$13-MIN(Parameters!$B$13,MAX(0,F6-Parameters!$B$13*4)))+MAX(0,Parameters!$B$13-MIN(Parameters!$B$13,MAX(0,G6-Parameters!$B$13*4)))+MAX(0,Parameters!$B$13-MIN(Parameters!$B$13,MAX(0,H6-Parameters!$B$13*4))))*Parameters!$B$6 -> 0 | G15: =(MAX(0,Parameters!$B$13-MIN(Parameters!$B$13,MAX(0,B6-Parameters!$B$13*5)))+MAX(0,Parameters!$B$13-MIN(Parameters!$B$13,MAX(0,C6-Parameters!$B$13*5)))+MAX(0,Parameters!$B$13-MIN(Parameters!$B$13,MAX(0,D6-Parameters!$B$13*5)))+MAX(0,Parameters!$B$13-MIN(Parameters!$B$13,MAX(0,E6-Parameters!$B$13*5)))+MAX(0,Parameters!$B$13-MIN(Parameters!$B$13,MAX(0,F6-Parameters!$B$13*5)))+MAX(0,Parameters!$B$13-MIN(Parameters!$B$13,MAX(0,G6-Parameters!$B$13*5)))+MAX(0,Parameters!$B$13-MIN(Parameters!$B$13,MAX(0,H6-Parameters!$B$13*5))))*Parameters!$B$6 -> 0 | H15: =(MAX(0,Parameters!$B$13-MIN(Parameters!$B$13,MAX(0,B6-Parameters!$B$13*6)))+MAX(0,Parameters!$B$13-MIN(Parameters!$B$13,MAX(0,C6-Parameters!$B$13*6)))+MAX(0,Parameters!$B$13-MIN(Parameters!$B$13,MAX(0,D6-Parameters!$B$13*6)))+MAX(0,Parameters!$B$13-MIN(Parameters!$B$13,MAX(0,E6-Parameters!$B$13*6)))+MAX(0,Parameters!$B$13-MIN(Parameters!$B$13,MAX(0,F6-Parameters!$B$13*6)))+MAX(0,Parameters!$B$13-MIN(Parameters!$B$13,MAX(0,G6-Parameters!$B$13*6)))+MAX(0,Parameters!$B$13-MIN(Parameters!$B$13,MAX(0,H6-Parameters!$B$13*6))))*Parameters!$B$6 -> 35 | I15: =(MAX(0,Parameters!$B$13-MIN(Parameters!$B$13,MAX(0,B6-Parameters!$B$13*7)))+MAX(0,Parameters!$B$13-MIN(Parameters!$B$13,MAX(0,C6-Parameters!$B$13*7)))+MAX(0,Parameters!$B$13-MIN(Parameters!$B$13,MAX(0,D6-Parameters!$B$13*7)))+MAX(0,Parameters!$B$13-MIN(Parameters!$B$13,MAX(0,E6-Parameters!$B$13*7)))+MAX(0,Parameters!$B$13-MIN(Parameters!$B$13,MAX(0,F6-Parameters!$B$13*7)))+MAX(0,Parameters!$B$13-MIN(Parameters!$B$13,MAX(0,G6-Parameters!$B$13*7)))+MAX(0,Parameters!$B$13-MIN(Parameters!$B$13,MAX(0,H6-Parameters!$B$13*7))))*Parameters!$B$6 -> 105 | J15: =SUM(B15:I15) -> 140 | K15: =COUNTIF(B15:I15,"<"&Parameters!$B$5) -> 7
A16: =A7 -> Spike (Ruby) | B16: =(MAX(0,Parameters!$B$13-MIN(Parameters!$B$13,MAX(0,B7-Parameters!$B$13*0)))+MAX(0,Parameters!$B$13-MIN(Parameters!$B$13,MAX(0,C7-Parameters!$B$13*0)))+MAX(0,Parameters!$B$13-MIN(Parameters!$B$13,MAX(0,D7-Parameters!$B$13*0)))+MAX(0,Parameters!$B$13-MIN(Parameters!$B$13,MAX(0,E7-Parameters!$B$13*0)))+MAX(0,Parameters!$B$13-MIN(Parameters!$B$13,MAX(0,F7-Parameters!$B$13*0)))+MAX(0,Parameters!$B$13-MIN(Parameters!$B$13,MAX(0,G7-Parameters!$B$13*0)))+MAX(0,Parameters!$B$13-MIN(Parameters!$B$13,MAX(0,H7-Parameters!$B$13*0))))*Parameters!$B$6 -> 30 | C16: =(MAX(0,Parameters!$B$13-MIN(Parameters!$B$13,MAX(0,B7-Parameters!$B$13*1)))+MAX(0,Parameters!$B$13-MIN(Parameters!$B$13,MAX(0,C7-Parameters!$B$13*1)))+MAX(0,Parameters!$B$13-MIN(Parameters!$B$13,MAX(0,D7-Parameters!$B$13*1)))+MAX(0,Parameters!$B$13-MIN(Parameters!$B$13,MAX(0,E7-Parameters!$B$13*1)))+MAX(0,Parameters!$B$13-MIN(Parameters!$B$13,MAX(0,F7-Parameters!$B$13*1)))+MAX(0,Parameters!$B$13-MIN(Parameters!$B$13,MAX(0,G7-Parameters!$B$13*1)))+MAX(0,Parameters!$B$13-MIN(Parameters!$B$13,MAX(0,H7-Parameters!$B$13*1))))*Parameters!$B$6 -> 90 | D16: =(MAX(0,Parameters!$B$13-MIN(Parameters!$B$13,MAX(0,B7-Parameters!$B$13*2)))+MAX(0,Parameters!$B$13-MIN(Parameters!$B$13,MAX(0,C7-Parameters!$B$13*2)))+MAX(0,Parameters!$B$13-MIN(Parameters!$B$13,MAX(0,D7-Parameters!$B$13*2)))+MAX(0,Parameters!$B$13-MIN(Parameters!$B$13,MAX(0,E7-Parameters!$B$13*2)))+MAX(0,Parameters!$B$13-MIN(Parameters!$B$13,MAX(0,F7-Parameters!$B$13*2)))+MAX(0,Parameters!$B$13-MIN(Parameters!$B$13,MAX(0,G7-Parameters!$B$13*2)))+MAX(0,Parameters!$B$13-MIN(Parameters!$B$13,MAX(0,H7-Parameters!$B$13*2))))*Parameters!$B$6 -> 90 | E16: =(MAX(0,Parameters!$B$13-MIN(Parameters!$B$13,MAX(0,B7-Parameters!$B$13*3)))+MAX(0,Parameters!$B$13-MIN(Parameters!$B$13,MAX(0,C7-Parameters!$B$13*3)))+MAX(0,Parameters!$B$13-MIN(Parameters!$B$13,MAX(0,D7-Parameters!$B$13*3)))+MAX(0,Parameters!$B$13-MIN(Parameters!$B$13,MAX(0,E7-Parameters!$B$13*3)))+MAX(0,Parameters!$B$13-MIN(Parameters!$B$13,MAX(0,F7-Parameters!$B$13*3)))+MAX(0,Parameters!$B$13-MIN(Parameters!$B$13,MAX(0,G7-Parameters!$B$13*3)))+MAX(0,Parameters!$B$13-MIN(Parameters!$B$13,MAX(0,H7-Parameters!$B$13*3))))*Parameters!$B$6 -> 90 | F16: =(MAX(0,Parameters!$B$13-MIN(Parameters!$B$13,MAX(0,B7-Parameters!$B$13*4)))+MAX(0,Parameters!$B$13-MIN(Parameters!$B$13,MAX(0,C7-Parameters!$B$13*4)))+MAX(0,Parameters!$B$13-MIN(Parameters!$B$13,MAX(0,D7-Parameters!$B$13*4)))+MAX(0,Parameters!$B$13-MIN(Parameters!$B$13,MAX(0,E7-Parameters!$B$13*4)))+MAX(0,Parameters!$B$13-MIN(Parameters!$B$13,MAX(0,F7-Parameters!$B$13*4)))+MAX(0,Parameters!$B$13-MIN(Parameters!$B$13,MAX(0,G7-Parameters!$B$13*4)))+MAX(0,Parameters!$B$13-MIN(Parameters!$B$13,MAX(0,H7-Parameters!$B$13*4))))*Parameters!$B$6 -> 90 | G16: =(MAX(0,Parameters!$B$13-MIN(Parameters!$B$13,MAX(0,B7-Parameters!$B$13*5)))+MAX(0,Parameters!$B$13-MIN(Parameters!$B$13,MAX(0,C7-Parameters!$B$13*5)))+MAX(0,Parameters!$B$13-MIN(Parameters!$B$13,MAX(0,D7-Parameters!$B$13*5)))+MAX(0,Parameters!$B$13-MIN(Parameters!$B$13,MAX(0,E7-Parameters!$B$13*5)))+MAX(0,Parameters!$B$13-MIN(Parameters!$B$13,MAX(0,F7-Parameters!$B$13*5)))+MAX(0,Parameters!$B$13-MIN(Parameters!$B$13,MAX(0,G7-Parameters!$B$13*5)))+MAX(0,Parameters!$B$13-MIN(Parameters!$B$13,MAX(0,H7-Parameters!$B$13*5))))*Parameters!$B$6 -> 90 | H16: =(MAX(0,Parameters!$B$13-MIN(Parameters!$B$13,MAX(0,B7-Parameters!$B$13*6)))+MAX(0,Parameters!$B$13-MIN(Parameters!$B$13,MAX(0,C7-Parameters!$B$13*6)))+MAX(0,Parameters!$B$13-MIN(Parameters!$B$13,MAX(0,D7-Parameters!$B$13*6)))+MAX(0,Parameters!$B$13-MIN(Parameters!$B$13,MAX(0,E7-Parameters!$B$13*6)))+MAX(0,Parameters!$B$13-MIN(Parameters!$B$13,MAX(0,F7-Parameters!$B$13*6)))+MAX(0,Parameters!$B$13-MIN(Parameters!$B$13,MAX(0,G7-Parameters!$B$13*6)))+MAX(0,Parameters!$B$13-MIN(Parameters!$B$13,MAX(0,H7-Parameters!$B$13*6))))*Parameters!$B$6 -> 90 | I16: =(MAX(0,Parameters!$B$13-MIN(Parameters!$B$13,MAX(0,B7-Parameters!$B$13*7)))+MAX(0,Parameters!$B$13-MIN(Parameters!$B$13,MAX(0,C7-Parameters!$B$13*7)))+MAX(0,Parameters!$B$13-MIN(Parameters!$B$13,MAX(0,D7-Parameters!$B$13*7)))+MAX(0,Parameters!$B$13-MIN(Parameters!$B$13,MAX(0,E7-Parameters!$B$13*7)))+MAX(0,Parameters!$B$13-MIN(Parameters!$B$13,MAX(0,F7-Parameters!$B$13*7)))+MAX(0,Parameters!$B$13-MIN(Parameters!$B$13,MAX(0,G7-Parameters!$B$13*7)))+MAX(0,Parameters!$B$13-MIN(Parameters!$B$13,MAX(0,H7-Parameters!$B$13*7))))*Parameters!$B$6 -> 90 | J16: =SUM(B16:I16) -> 660 | K16: =COUNTIF(B16:I16,"<"&Parameters!$B$5) -> 8
A17: =A8 -> Lopsided | B17: =(MAX(0,Parameters!$B$13-MIN(Parameters!$B$13,MAX(0,B8-Parameters!$B$13*0)))+MAX(0,Parameters!$B$13-MIN(Parameters!$B$13,MAX(0,C8-Parameters!$B$13*0)))+MAX(0,Parameters!$B$13-MIN(Parameters!$B$13,MAX(0,D8-Parameters!$B$13*0)))+MAX(0,Parameters!$B$13-MIN(Parameters!$B$13,MAX(0,E8-Parameters!$B$13*0)))+MAX(0,Parameters!$B$13-MIN(Parameters!$B$13,MAX(0,F8-Parameters!$B$13*0)))+MAX(0,Parameters!$B$13-MIN(Parameters!$B$13,MAX(0,G8-Parameters!$B$13*0)))+MAX(0,Parameters!$B$13-MIN(Parameters!$B$13,MAX(0,H8-Parameters!$B$13*0))))*Parameters!$B$6 -> 0 | C17: =(MAX(0,Parameters!$B$13-MIN(Parameters!$B$13,MAX(0,B8-Parameters!$B$13*1)))+MAX(0,Parameters!$B$13-MIN(Parameters!$B$13,MAX(0,C8-Parameters!$B$13*1)))+MAX(0,Parameters!$B$13-MIN(Parameters!$B$13,MAX(0,D8-Parameters!$B$13*1)))+MAX(0,Parameters!$B$13-MIN(Parameters!$B$13,MAX(0,E8-Parameters!$B$13*1)))+MAX(0,Parameters!$B$13-MIN(Parameters!$B$13,MAX(0,F8-Parameters!$B$13*1)))+MAX(0,Parameters!$B$13-MIN(Parameters!$B$13,MAX(0,G8-Parameters!$B$13*1)))+MAX(0,Parameters!$B$13-MIN(Parameters!$B$13,MAX(0,H8-Parameters!$B$13*1))))*Parameters!$B$6 -> 20 | D17: =(MAX(0,Parameters!$B$13-MIN(Parameters!$B$13,MAX(0,B8-Parameters!$B$13*2)))+MAX(0,Parameters!$B$13-MIN(Parameters!$B$13,MAX(0,C8-Parameters!$B$13*2)))+MAX(0,Parameters!$B$13-MIN(Parameters!$B$13,MAX(0,D8-Parameters!$B$13*2)))+MAX(0,Parameters!$B$13-MIN(Parameters!$B$13,MAX(0,E8-Parameters!$B$13*2)))+MAX(0,Parameters!$B$13-MIN(Parameters!$B$13,MAX(0,F8-Parameters!$B$13*2)))+MAX(0,Parameters!$B$13-MIN(Parameters!$B$13,MAX(0,G8-Parameters!$B$13*2)))+MAX(0,Parameters!$B$13-MIN(Parameters!$B$13,MAX(0,H8-Parameters!$B$13*2))))*Parameters!$B$6 -> 60 | E17: =(MAX(0,Parameters!$B$13-MIN(Parameters!$B$13,MAX(0,B8-Parameters!$B$13*3)))+MAX(0,Parameters!$B$13-MIN(Parameters!$B$13,MAX(0,C8-Parameters!$B$13*3)))+MAX(0,Parameters!$B$13-MIN(Parameters!$B$13,MAX(0,D8-Parameters!$B$13*3)))+MAX(0,Parameters!$B$13-MIN(Parameters!$B$13,MAX(0,E8-Parameters!$B$13*3)))+MAX(0,Parameters!$B$13-MIN(Parameters!$B$13,MAX(0,F8-Parameters!$B$13*3)))+MAX(0,Parameters!$B$13-MIN(Parameters!$B$13,MAX(0,G8-Parameters!$B$13*3)))+MAX(0,Parameters!$B$13-MIN(Parameters!$B$13,MAX(0,H8-Parameters!$B$13*3))))*Parameters!$B$6 -> 60 | F17: =(MAX(0,Parameters!$B$13-MIN(Parameters!$B$13,MAX(0,B8-Parameters!$B$13*4)))+MAX(0,Parameters!$B$13-MIN(Parameters!$B$13,MAX(0,C8-Parameters!$B$13*4)))+MAX(0,Parameters!$B$13-MIN(Parameters!$B$13,MAX(0,D8-Parameters!$B$13*4)))+MAX(0,Parameters!$B$13-MIN(Parameters!$B$13,MAX(0,E8-Parameters!$B$13*4)))+MAX(0,Parameters!$B$13-MIN(Parameters!$B$13,MAX(0,F8-Parameters!$B$13*4)))+MAX(0,Parameters!$B$13-MIN(Parameters!$B$13,MAX(0,G8-Parameters!$B$13*4)))+MAX(0,Parameters!$B$13-MIN(Parameters!$B$13,MAX(0,H8-Parameters!$B$13*4))))*Parameters!$B$6 -> 60 | G17: =(MAX(0,Parameters!$B$13-MIN(Parameters!$B$13,MAX(0,B8-Parameters!$B$13*5)))+MAX(0,Parameters!$B$13-MIN(Parameters!$B$13,MAX(0,C8-Parameters!$B$13*5)))+MAX(0,Parameters!$B$13-MIN(Parameters!$B$13,MAX(0,D8-Parameters!$B$13*5)))+MAX(0,Parameters!$B$13-MIN(Parameters!$B$13,MAX(0,E8-Parameters!$B$13*5)))+MAX(0,Parameters!$B$13-MIN(Parameters!$B$13,MAX(0,F8-Parameters!$B$13*5)))+MAX(0,Parameters!$B$13-MIN(Parameters!$B$13,MAX(0,G8-Parameters!$B$13*5)))+MAX(0,Parameters!$B$13-MIN(Parameters!$B$13,MAX(0,H8-Parameters!$B$13*5))))*Parameters!$B$6 -> 60 | H17: =(MAX(0,Parameters!$B$13-MIN(Parameters!$B$13,MAX(0,B8-Parameters!$B$13*6)))+MAX(0,Parameters!$B$13-MIN(Parameters!$B$13,MAX(0,C8-Parameters!$B$13*6)))+MAX(0,Parameters!$B$13-MIN(Parameters!$B$13,MAX(0,D8-Parameters!$B$13*6)))+MAX(0,Parameters!$B$13-MIN(Parameters!$B$13,MAX(0,E8-Parameters!$B$13*6)))+MAX(0,Parameters!$B$13-MIN(Parameters!$B$13,MAX(0,F8-Parameters!$B$13*6)))+MAX(0,Parameters!$B$13-MIN(Parameters!$B$13,MAX(0,G8-Parameters!$B$13*6)))+MAX(0,Parameters!$B$13-MIN(Parameters!$B$13,MAX(0,H8-Parameters!$B$13*6))))*Parameters!$B$6 -> 60 | I17: =(MAX(0,Parameters!$B$13-MIN(Parameters!$B$13,MAX(0,B8-Parameters!$B$13*7)))+MAX(0,Parameters!$B$13-MIN(Parameters!$B$13,MAX(0,C8-Parameters!$B$13*7)))+MAX(0,Parameters!$B$13-MIN(Parameters!$B$13,MAX(0,D8-Parameters!$B$13*7)))+MAX(0,Parameters!$B$13-MIN(Parameters!$B$13,MAX(0,E8-Parameters!$B$13*7)))+MAX(0,Parameters!$B$13-MIN(Parameters!$B$13,MAX(0,F8-Parameters!$B$13*7)))+MAX(0,Parameters!$B$13-MIN(Parameters!$B$13,MAX(0,G8-Parameters!$B$13*7)))+MAX(0,Parameters!$B$13-MIN(Parameters!$B$13,MAX(0,H8-Parameters!$B$13*7))))*Parameters!$B$6 -> 60 | J17: =SUM(B17:I17) -> 380 | K17: =COUNTIF(B17:I17,"<"&Parameters!$B$5) -> 8
A18: =A9 -> Burst | B18: =(MAX(0,Parameters!$B$13-MIN(Parameters!$B$13,MAX(0,B9-Parameters!$B$13*0)))+MAX(0,Parameters!$B$13-MIN(Parameters!$B$13,MAX(0,C9-Parameters!$B$13*0)))+MAX(0,Parameters!$B$13-MIN(Parameters!$B$13,MAX(0,D9-Parameters!$B$13*0)))+MAX(0,Parameters!$B$13-MIN(Parameters!$B$13,MAX(0,E9-Parameters!$B$13*0)))+MAX(0,Parameters!$B$13-MIN(Parameters!$B$13,MAX(0,F9-Parameters!$B$13*0)))+MAX(0,Parameters!$B$13-MIN(Parameters!$B$13,MAX(0,G9-Parameters!$B$13*0)))+MAX(0,Parameters!$B$13-MIN(Parameters!$B$13,MAX(0,H9-Parameters!$B$13*0))))*Parameters!$B$6 -> 0 | C18: =(MAX(0,Parameters!$B$13-MIN(Parameters!$B$13,MAX(0,B9-Parameters!$B$13*1)))+MAX(0,Parameters!$B$13-MIN(Parameters!$B$13,MAX(0,C9-Parameters!$B$13*1)))+MAX(0,Parameters!$B$13-MIN(Parameters!$B$13,MAX(0,D9-Parameters!$B$13*1)))+MAX(0,Parameters!$B$13-MIN(Parameters!$B$13,MAX(0,E9-Parameters!$B$13*1)))+MAX(0,Parameters!$B$13-MIN(Parameters!$B$13,MAX(0,F9-Parameters!$B$13*1)))+MAX(0,Parameters!$B$13-MIN(Parameters!$B$13,MAX(0,G9-Parameters!$B$13*1)))+MAX(0,Parameters!$B$13-MIN(Parameters!$B$13,MAX(0,H9-Parameters!$B$13*1))))*Parameters!$B$6 -> 0 | D18: =(MAX(0,Parameters!$B$13-MIN(Parameters!$B$13,MAX(0,B9-Parameters!$B$13*2)))+MAX(0,Parameters!$B$13-MIN(Parameters!$B$13,MAX(0,C9-Parameters!$B$13*2)))+MAX(0,Parameters!$B$13-MIN(Parameters!$B$13,MAX(0,D9-Parameters!$B$13*2)))+MAX(0,Parameters!$B$13-MIN(Parameters!$B$13,MAX(0,E9-Parameters!$B$13*2)))+MAX(0,Parameters!$B$13-MIN(Parameters!$B$13,MAX(0,F9-Parameters!$B$13*2)))+MAX(0,Parameters!$B$13-MIN(Parameters!$B$13,MAX(0,G9-Parameters!$B$13*2)))+MAX(0,Parameters!$B$13-MIN(Parameters!$B$13,MAX(0,H9-Parameters!$B$13*2))))*Parameters!$B$6 -> 0 | E18: =(MAX(0,Parameters!$B$13-MIN(Parameters!$B$13,MAX(0,B9-Parameters!$B$13*3)))+MAX(0,Parameters!$B$13-MIN(Parameters!$B$13,MAX(0,C9-Parameters!$B$13*3)))+MAX(0,Parameters!$B$13-MIN(Parameters!$B$13,MAX(0,D9-Parameters!$B$13*3)))+MAX(0,Parameters!$B$13-MIN(Parameters!$B$13,MAX(0,E9-Parameters!$B$13*3)))+MAX(0,Parameters!$B$13-MIN(Parameters!$B$13,MAX(0,F9-Parameters!$B$13*3)))+MAX(0,Parameters!$B$13-MIN(Parameters!$B$13,MAX(0,G9-Parameters!$B$13*3)))+MAX(0,Parameters!$B$13-MIN(Parameters!$B$13,MAX(0,H9-Parameters!$B$13*3))))*Parameters!$B$6 -> 0 | F18: =(MAX(0,Parameters!$B$13-MIN(Parameters!$B$13,MAX(0,B9-Parameters!$B$13*4)))+MAX(0,Parameters!$B$13-MIN(Parameters!$B$13,MAX(0,C9-Parameters!$B$13*4)))+MAX(0,Parameters!$B$13-MIN(Parameters!$B$13,MAX(0,D9-Parameters!$B$13*4)))+MAX(0,Parameters!$B$13-MIN(Parameters!$B$13,MAX(0,E9-Parameters!$B$13*4)))+MAX(0,Parameters!$B$13-MIN(Parameters!$B$13,MAX(0,F9-Parameters!$B$13*4)))+MAX(0,Parameters!$B$13-MIN(Parameters!$B$13,MAX(0,G9-Parameters!$B$13*4)))+MAX(0,Parameters!$B$13-MIN(Parameters!$B$13,MAX(0,H9-Parameters!$B$13*4))))*Parameters!$B$6 -> 0 | G18: =(MAX(0,Parameters!$B$13-MIN(Parameters!$B$13,MAX(0,B9-Parameters!$B$13*5)))+MAX(0,Parameters!$B$13-MIN(Parameters!$B$13,MAX(0,C9-Parameters!$B$13*5)))+MAX(0,Parameters!$B$13-MIN(Parameters!$B$13,MAX(0,D9-Parameters!$B$13*5)))+MAX(0,Parameters!$B$13-MIN(Parameters!$B$13,MAX(0,E9-Parameters!$B$13*5)))+MAX(0,Parameters!$B$13-MIN(Parameters!$B$13,MAX(0,F9-Parameters!$B$13*5)))+MAX(0,Parameters!$B$13-MIN(Parameters!$B$13,MAX(0,G9-Parameters!$B$13*5)))+MAX(0,Parameters!$B$13-MIN(Parameters!$B$13,MAX(0,H9-Parameters!$B$13*5))))*Parameters!$B$6 -> 0 | H18: =(MAX(0,Parameters!$B$13-MIN(Parameters!$B$13,MAX(0,B9-Parameters!$B$13*6)))+MAX(0,Parameters!$B$13-MIN(Parameters!$B$13,MAX(0,C9-Parameters!$B$13*6)))+MAX(0,Parameters!$B$13-MIN(Parameters!$B$13,MAX(0,D9-Parameters!$B$13*6)))+MAX(0,Parameters!$B$13-MIN(Parameters!$B$13,MAX(0,E9-Parameters!$B$13*6)))+MAX(0,Parameters!$B$13-MIN(Parameters!$B$13,MAX(0,F9-Parameters!$B$13*6)))+MAX(0,Parameters!$B$13-MIN(Parameters!$B$13,MAX(0,G9-Parameters!$B$13*6)))+MAX(0,Parameters!$B$13-MIN(Parameters!$B$13,MAX(0,H9-Parameters!$B$13*6))))*Parameters!$B$6 -> 35 | I18: =(MAX(0,Parameters!$B$13-MIN(Parameters!$B$13,MAX(0,B9-Parameters!$B$13*7)))+MAX(0,Parameters!$B$13-MIN(Parameters!$B$13,MAX(0,C9-Parameters!$B$13*7)))+MAX(0,Parameters!$B$13-MIN(Parameters!$B$13,MAX(0,D9-Parameters!$B$13*7)))+MAX(0,Parameters!$B$13-MIN(Parameters!$B$13,MAX(0,E9-Parameters!$B$13*7)))+MAX(0,Parameters!$B$13-MIN(Parameters!$B$13,MAX(0,F9-Parameters!$B$13*7)))+MAX(0,Parameters!$B$13-MIN(Parameters!$B$13,MAX(0,G9-Parameters!$B$13*7)))+MAX(0,Parameters!$B$13-MIN(Parameters!$B$13,MAX(0,H9-Parameters!$B$13*7))))*Parameters!$B$6 -> 105 | J18: =SUM(B18:I18) -> 140 | K18: =COUNTIF(B18:I18,"<"&Parameters!$B$5) -> 7
A20: Max traversals counts how many single traversals cost less than full vitality. Rough guide, not cumulative.
A22: REALM DEPTH
A23: After arriving, how many workings can be cast in the strongest hue before that pool is dry.
A24: Build | B24: Strongest pool | C24: After 1 traversal | D24: Workings available | E24: After 2 traversals | F24: Workings available | G24: Magnitude wall? | H24: Breadth wall?
A25: =A6 -> Balanced | B25: =MAX(B6:H6) -> 100 | C25: =MAX(0,B25-Parameters!$B$13) -> 85 | D25: =ROUNDDOWN(C25/Parameters!$B$14,0) -> 10 | E25: =MAX(0,B25-Parameters!$B$13*2) -> 70 | F25: =ROUNDDOWN(E25/Parameters!$B$14,0) -> 8 | G25: =IF(B25>=Parameters!$B$25,"PASS","fail") -> fail | H25: =IF(COUNTIF(B6:H6,">="&Parameters!$B$26)>=4,"PASS","fail") -> PASS
A26: =A7 -> Spike (Ruby) | B26: =MAX(B7:H7) -> 640 | C26: =MAX(0,B26-Parameters!$B$13) -> 625 | D26: =ROUNDDOWN(C26/Parameters!$B$14,0) -> 78 | E26: =MAX(0,B26-Parameters!$B$13*2) -> 610 | F26: =ROUNDDOWN(E26/Parameters!$B$14,0) -> 76 | G26: =IF(B26>=Parameters!$B$25,"PASS","fail") -> PASS | H26: =IF(COUNTIF(B7:H7,">="&Parameters!$B$26)>=4,"PASS","fail") -> fail
A27: =A8 -> Lopsided | B27: =MAX(B8:H8) -> 250 | C27: =MAX(0,B27-Parameters!$B$13) -> 235 | D27: =ROUNDDOWN(C27/Parameters!$B$14,0) -> 29 | E27: =MAX(0,B27-Parameters!$B$13*2) -> 220 | F27: =ROUNDDOWN(E27/Parameters!$B$14,0) -> 27 | G27: =IF(B27>=Parameters!$B$25,"PASS","fail") -> fail | H27: =IF(COUNTIF(B8:H8,">="&Parameters!$B$26)>=4,"PASS","fail") -> fail
A28: =A9 -> Burst | B28: =MAX(B9:H9) -> 100 | C28: =MAX(0,B28-Parameters!$B$13) -> 85 | D28: =ROUNDDOWN(C28/Parameters!$B$14,0) -> 10 | E28: =MAX(0,B28-Parameters!$B$13*2) -> 70 | F28: =ROUNDDOWN(E28/Parameters!$B$14,0) -> 8 | G28: =IF(B28>=Parameters!$B$25,"PASS","fail") -> fail | H28: =IF(COUNTIF(B9:H9,">="&Parameters!$B$26)>=4,"PASS","fail") -> PASS

Sheet Run Ledger
A1: Run Ledger
A2: One run, step by step. Edit column B (Travel / Work / Gather) and column C (hue 1-7) to test a route. Row 6 is the starting state - edit it or link it to a build.
A4: Starting pools | B4: =IF(TRUE(),"Edit row 6 directly, or paste a build's allocation into D6:J6","") -> Edit row 6 directly, or paste a build's allocation into D6:J6
A5: Step | B5: Action | C5: Hue | D5: Amber | E5: Citrine | F5: Emerald | G5: Sapphire | H5: Iolite | I5: Amethyst | J5: Ruby | K5: Vitality | L5: Overflow | M5: State | O5: RUN SUMMARY
A6: 0 | B6: START | D6: ='Build Comparison'!B$6 -> 100 | E6: ='Build Comparison'!C$6 -> 100 | F6: ='Build Comparison'!D$6 -> 100 | G6: ='Build Comparison'!E$6 -> 100 | H6: ='Build Comparison'!F$6 -> 100 | I6: ='Build Comparison'!G$6 -> 100 | J6: ='Build Comparison'!H$6 -> 100 | K6: =Parameters!$B$5 -> 100 | L6: 0 | M6: alive | O6: Actions completed | P6: =COUNTIF(M7:M51,"alive") -> 33
A7: 1 | B7: Travel | D7: =IF($K6<=0,D6,IF($B7="Travel",MAX(0,D6-Parameters!$B$13),IF(AND($B7="Work",$C7=1),MAX(0,D6-Parameters!$B$14),IF(AND($B7="Gather",$C7=1),MIN(Parameters!$B$10,D6+Parameters!$B$16),D6)))) -> 85 | E7: =IF($K6<=0,E6,IF($B7="Travel",MAX(0,E6-Parameters!$B$13),IF(AND($B7="Work",$C7=2),MAX(0,E6-Parameters!$B$14),IF(AND($B7="Gather",$C7=2),MIN(Parameters!$B$10,E6+Parameters!$B$16),E6)))) -> 85 | F7: =IF($K6<=0,F6,IF($B7="Travel",MAX(0,F6-Parameters!$B$13),IF(AND($B7="Work",$C7=3),MAX(0,F6-Parameters!$B$14),IF(AND($B7="Gather",$C7=3),MIN(Parameters!$B$10,F6+Parameters!$B$16),F6)))) -> 85 | G7: =IF($K6<=0,G6,IF($B7="Travel",MAX(0,G6-Parameters!$B$13),IF(AND($B7="Work",$C7=4),MAX(0,G6-Parameters!$B$14),IF(AND($B7="Gather",$C7=4),MIN(Parameters!$B$10,G6+Parameters!$B$16),G6)))) -> 85 | H7: =IF($K6<=0,H6,IF($B7="Travel",MAX(0,H6-Parameters!$B$13),IF(AND($B7="Work",$C7=5),MAX(0,H6-Parameters!$B$14),IF(AND($B7="Gather",$C7=5),MIN(Parameters!$B$10,H6+Parameters!$B$16),H6)))) -> 85 | I7: =IF($K6<=0,I6,IF($B7="Travel",MAX(0,I6-Parameters!$B$13),IF(AND($B7="Work",$C7=6),MAX(0,I6-Parameters!$B$14),IF(AND($B7="Gather",$C7=6),MIN(Parameters!$B$10,I6+Parameters!$B$16),I6)))) -> 85 | J7: =IF($K6<=0,J6,IF($B7="Travel",MAX(0,J6-Parameters!$B$13),IF(AND($B7="Work",$C7=7),MAX(0,J6-Parameters!$B$14),IF(AND($B7="Gather",$C7=7),MIN(Parameters!$B$10,J6+Parameters!$B$16),J6)))) -> 85 | K7: =IF($K6<=0,0,MAX(0,K6-L7*Parameters!$B$6-IF($B7="Gather",Parameters!$B$17,0))) -> 100 | L7: =IF($K6<=0,0,MAX(0,IF($B7="Travel",Parameters!$B$13*7,IF($B7="Work",Parameters!$B$14,0))-(SUM(D6:J6)-SUM(D7:J7)))) -> 0 | M7: =IF(K7<=0,"RUN OVER","alive") -> alive | O7: Vitality remaining | P7: =K51 -> 0
A8: 2 | B8: Work | C8: 7 | D8: =IF($K7<=0,D7,IF($B8="Travel",MAX(0,D7-Parameters!$B$13),IF(AND($B8="Work",$C8=1),MAX(0,D7-Parameters!$B$14),IF(AND($B8="Gather",$C8=1),MIN(Parameters!$B$10,D7+Parameters!$B$16),D7)))) -> 85 | E8: =IF($K7<=0,E7,IF($B8="Travel",MAX(0,E7-Parameters!$B$13),IF(AND($B8="Work",$C8=2),MAX(0,E7-Parameters!$B$14),IF(AND($B8="Gather",$C8=2),MIN(Parameters!$B$10,E7+Parameters!$B$16),E7)))) -> 85 | F8: =IF($K7<=0,F7,IF($B8="Travel",MAX(0,F7-Parameters!$B$13),IF(AND($B8="Work",$C8=3),MAX(0,F7-Parameters!$B$14),IF(AND($B8="Gather",$C8=3),MIN(Parameters!$B$10,F7+Parameters!$B$16),F7)))) -> 85 | G8: =IF($K7<=0,G7,IF($B8="Travel",MAX(0,G7-Parameters!$B$13),IF(AND($B8="Work",$C8=4),MAX(0,G7-Parameters!$B$14),IF(AND($B8="Gather",$C8=4),MIN(Parameters!$B$10,G7+Parameters!$B$16),G7)))) -> 85 | H8: =IF($K7<=0,H7,IF($B8="Travel",MAX(0,H7-Parameters!$B$13),IF(AND($B8="Work",$C8=5),MAX(0,H7-Parameters!$B$14),IF(AND($B8="Gather",$C8=5),MIN(Parameters!$B$10,H7+Parameters!$B$16),H7)))) -> 85 | I8: =IF($K7<=0,I7,IF($B8="Travel",MAX(0,I7-Parameters!$B$13),IF(AND($B8="Work",$C8=6),MAX(0,I7-Parameters!$B$14),IF(AND($B8="Gather",$C8=6),MIN(Parameters!$B$10,I7+Parameters!$B$16),I7)))) -> 85 | J8: =IF($K7<=0,J7,IF($B8="Travel",MAX(0,J7-Parameters!$B$13),IF(AND($B8="Work",$C8=7),MAX(0,J7-Parameters!$B$14),IF(AND($B8="Gather",$C8=7),MIN(Parameters!$B$10,J7+Parameters!$B$16),J7)))) -> 77 | K8: =IF($K7<=0,0,MAX(0,K7-L8*Parameters!$B$6-IF($B8="Gather",Parameters!$B$17,0))) -> 100 | L8: =IF($K7<=0,0,MAX(0,IF($B8="Travel",Parameters!$B$13*7,IF($B8="Work",Parameters!$B$14,0))-(SUM(D7:J7)-SUM(D8:J8)))) -> 0 | M8: =IF(K8<=0,"RUN OVER","alive") -> alive | O8: Traversals made | P8: =COUNTIFS(B7:B51,"Travel",M7:M51,"alive") -> 3
A9: 3 | B9: Work | C9: 7 | D9: =IF($K8<=0,D8,IF($B9="Travel",MAX(0,D8-Parameters!$B$13),IF(AND($B9="Work",$C9=1),MAX(0,D8-Parameters!$B$14),IF(AND($B9="Gather",$C9=1),MIN(Parameters!$B$10,D8+Parameters!$B$16),D8)))) -> 85 | E9: =IF($K8<=0,E8,IF($B9="Travel",MAX(0,E8-Parameters!$B$13),IF(AND($B9="Work",$C9=2),MAX(0,E8-Parameters!$B$14),IF(AND($B9="Gather",$C9=2),MIN(Parameters!$B$10,E8+Parameters!$B$16),E8)))) -> 85 | F9: =IF($K8<=0,F8,IF($B9="Travel",MAX(0,F8-Parameters!$B$13),IF(AND($B9="Work",$C9=3),MAX(0,F8-Parameters!$B$14),IF(AND($B9="Gather",$C9=3),MIN(Parameters!$B$10,F8+Parameters!$B$16),F8)))) -> 85 | G9: =IF($K8<=0,G8,IF($B9="Travel",MAX(0,G8-Parameters!$B$13),IF(AND($B9="Work",$C9=4),MAX(0,G8-Parameters!$B$14),IF(AND($B9="Gather",$C9=4),MIN(Parameters!$B$10,G8+Parameters!$B$16),G8)))) -> 85 | H9: =IF($K8<=0,H8,IF($B9="Travel",MAX(0,H8-Parameters!$B$13),IF(AND($B9="Work",$C9=5),MAX(0,H8-Parameters!$B$14),IF(AND($B9="Gather",$C9=5),MIN(Parameters!$B$10,H8+Parameters!$B$16),H8)))) -> 85 | I9: =IF($K8<=0,I8,IF($B9="Travel",MAX(0,I8-Parameters!$B$13),IF(AND($B9="Work",$C9=6),MAX(0,I8-Parameters!$B$14),IF(AND($B9="Gather",$C9=6),MIN(Parameters!$B$10,I8+Parameters!$B$16),I8)))) -> 85 | J9: =IF($K8<=0,J8,IF($B9="Travel",MAX(0,J8-Parameters!$B$13),IF(AND($B9="Work",$C9=7),MAX(0,J8-Parameters!$B$14),IF(AND($B9="Gather",$C9=7),MIN(Parameters!$B$10,J8+Parameters!$B$16),J8)))) -> 69 | K9: =IF($K8<=0,0,MAX(0,K8-L9*Parameters!$B$6-IF($B9="Gather",Parameters!$B$17,0))) -> 100 | L9: =IF($K8<=0,0,MAX(0,IF($B9="Travel",Parameters!$B$13*7,IF($B9="Work",Parameters!$B$14,0))-(SUM(D8:J8)-SUM(D9:J9)))) -> 0 | M9: =IF(K9<=0,"RUN OVER","alive") -> alive | O9: Workings cast | P9: =COUNTIFS(B7:B51,"Work",M7:M51,"alive") -> 28
A10: 4 | B10: Work | C10: 7 | D10: =IF($K9<=0,D9,IF($B10="Travel",MAX(0,D9-Parameters!$B$13),IF(AND($B10="Work",$C10=1),MAX(0,D9-Parameters!$B$14),IF(AND($B10="Gather",$C10=1),MIN(Parameters!$B$10,D9+Parameters!$B$16),D9)))) -> 85 | E10: =IF($K9<=0,E9,IF($B10="Travel",MAX(0,E9-Parameters!$B$13),IF(AND($B10="Work",$C10=2),MAX(0,E9-Parameters!$B$14),IF(AND($B10="Gather",$C10=2),MIN(Parameters!$B$10,E9+Parameters!$B$16),E9)))) -> 85 | F10: =IF($K9<=0,F9,IF($B10="Travel",MAX(0,F9-Parameters!$B$13),IF(AND($B10="Work",$C10=3),MAX(0,F9-Parameters!$B$14),IF(AND($B10="Gather",$C10=3),MIN(Parameters!$B$10,F9+Parameters!$B$16),F9)))) -> 85 | G10: =IF($K9<=0,G9,IF($B10="Travel",MAX(0,G9-Parameters!$B$13),IF(AND($B10="Work",$C10=4),MAX(0,G9-Parameters!$B$14),IF(AND($B10="Gather",$C10=4),MIN(Parameters!$B$10,G9+Parameters!$B$16),G9)))) -> 85 | H10: =IF($K9<=0,H9,IF($B10="Travel",MAX(0,H9-Parameters!$B$13),IF(AND($B10="Work",$C10=5),MAX(0,H9-Parameters!$B$14),IF(AND($B10="Gather",$C10=5),MIN(Parameters!$B$10,H9+Parameters!$B$16),H9)))) -> 85 | I10: =IF($K9<=0,I9,IF($B10="Travel",MAX(0,I9-Parameters!$B$13),IF(AND($B10="Work",$C10=6),MAX(0,I9-Parameters!$B$14),IF(AND($B10="Gather",$C10=6),MIN(Parameters!$B$10,I9+Parameters!$B$16),I9)))) -> 85 | J10: =IF($K9<=0,J9,IF($B10="Travel",MAX(0,J9-Parameters!$B$13),IF(AND($B10="Work",$C10=7),MAX(0,J9-Parameters!$B$14),IF(AND($B10="Gather",$C10=7),MIN(Parameters!$B$10,J9+Parameters!$B$16),J9)))) -> 61 | K10: =IF($K9<=0,0,MAX(0,K9-L10*Parameters!$B$6-IF($B10="Gather",Parameters!$B$17,0))) -> 100 | L10: =IF($K9<=0,0,MAX(0,IF($B10="Travel",Parameters!$B$13*7,IF($B10="Work",Parameters!$B$14,0))-(SUM(D9:J9)-SUM(D10:J10)))) -> 0 | M10: =IF(K10<=0,"RUN OVER","alive") -> alive | O10: Total overflow to vitality | P10: =SUM(L7:L51) -> 104
A11: 5 | B11: Work | C11: 7 | D11: =IF($K10<=0,D10,IF($B11="Travel",MAX(0,D10-Parameters!$B$13),IF(AND($B11="Work",$C11=1),MAX(0,D10-Parameters!$B$14),IF(AND($B11="Gather",$C11=1),MIN(Parameters!$B$10,D10+Parameters!$B$16),D10)))) -> 85 | E11: =IF($K10<=0,E10,IF($B11="Travel",MAX(0,E10-Parameters!$B$13),IF(AND($B11="Work",$C11=2),MAX(0,E10-Parameters!$B$14),IF(AND($B11="Gather",$C11=2),MIN(Parameters!$B$10,E10+Parameters!$B$16),E10)))) -> 85 | F11: =IF($K10<=0,F10,IF($B11="Travel",MAX(0,F10-Parameters!$B$13),IF(AND($B11="Work",$C11=3),MAX(0,F10-Parameters!$B$14),IF(AND($B11="Gather",$C11=3),MIN(Parameters!$B$10,F10+Parameters!$B$16),F10)))) -> 85 | G11: =IF($K10<=0,G10,IF($B11="Travel",MAX(0,G10-Parameters!$B$13),IF(AND($B11="Work",$C11=4),MAX(0,G10-Parameters!$B$14),IF(AND($B11="Gather",$C11=4),MIN(Parameters!$B$10,G10+Parameters!$B$16),G10)))) -> 85 | H11: =IF($K10<=0,H10,IF($B11="Travel",MAX(0,H10-Parameters!$B$13),IF(AND($B11="Work",$C11=5),MAX(0,H10-Parameters!$B$14),IF(AND($B11="Gather",$C11=5),MIN(Parameters!$B$10,H10+Parameters!$B$16),H10)))) -> 85 | I11: =IF($K10<=0,I10,IF($B11="Travel",MAX(0,I10-Parameters!$B$13),IF(AND($B11="Work",$C11=6),MAX(0,I10-Parameters!$B$14),IF(AND($B11="Gather",$C11=6),MIN(Parameters!$B$10,I10+Parameters!$B$16),I10)))) -> 85 | J11: =IF($K10<=0,J10,IF($B11="Travel",MAX(0,J10-Parameters!$B$13),IF(AND($B11="Work",$C11=7),MAX(0,J10-Parameters!$B$14),IF(AND($B11="Gather",$C11=7),MIN(Parameters!$B$10,J10+Parameters!$B$16),J10)))) -> 53 | K11: =IF($K10<=0,0,MAX(0,K10-L11*Parameters!$B$6-IF($B11="Gather",Parameters!$B$17,0))) -> 100 | L11: =IF($K10<=0,0,MAX(0,IF($B11="Travel",Parameters!$B$13*7,IF($B11="Work",Parameters!$B$14,0))-(SUM(D10:J10)-SUM(D11:J11)))) -> 0 | M11: =IF(K11<=0,"RUN OVER","alive") -> alive | O11: Run length (minutes) | P11: =IFERROR(P6*Parameters!$B$20/60,0) -> 2.2
A12: 6 | B12: Work | C12: 7 | D12: =IF($K11<=0,D11,IF($B12="Travel",MAX(0,D11-Parameters!$B$13),IF(AND($B12="Work",$C12=1),MAX(0,D11-Parameters!$B$14),IF(AND($B12="Gather",$C12=1),MIN(Parameters!$B$10,D11+Parameters!$B$16),D11)))) -> 85 | E12: =IF($K11<=0,E11,IF($B12="Travel",MAX(0,E11-Parameters!$B$13),IF(AND($B12="Work",$C12=2),MAX(0,E11-Parameters!$B$14),IF(AND($B12="Gather",$C12=2),MIN(Parameters!$B$10,E11+Parameters!$B$16),E11)))) -> 85 | F12: =IF($K11<=0,F11,IF($B12="Travel",MAX(0,F11-Parameters!$B$13),IF(AND($B12="Work",$C12=3),MAX(0,F11-Parameters!$B$14),IF(AND($B12="Gather",$C12=3),MIN(Parameters!$B$10,F11+Parameters!$B$16),F11)))) -> 85 | G12: =IF($K11<=0,G11,IF($B12="Travel",MAX(0,G11-Parameters!$B$13),IF(AND($B12="Work",$C12=4),MAX(0,G11-Parameters!$B$14),IF(AND($B12="Gather",$C12=4),MIN(Parameters!$B$10,G11+Parameters!$B$16),G11)))) -> 85 | H12: =IF($K11<=0,H11,IF($B12="Travel",MAX(0,H11-Parameters!$B$13),IF(AND($B12="Work",$C12=5),MAX(0,H11-Parameters!$B$14),IF(AND($B12="Gather",$C12=5),MIN(Parameters!$B$10,H11+Parameters!$B$16),H11)))) -> 85 | I12: =IF($K11<=0,I11,IF($B12="Travel",MAX(0,I11-Parameters!$B$13),IF(AND($B12="Work",$C12=6),MAX(0,I11-Parameters!$B$14),IF(AND($B12="Gather",$C12=6),MIN(Parameters!$B$10,I11+Parameters!$B$16),I11)))) -> 85 | J12: =IF($K11<=0,J11,IF($B12="Travel",MAX(0,J11-Parameters!$B$13),IF(AND($B12="Work",$C12=7),MAX(0,J11-Parameters!$B$14),IF(AND($B12="Gather",$C12=7),MIN(Parameters!$B$10,J11+Parameters!$B$16),J11)))) -> 45 | K12: =IF($K11<=0,0,MAX(0,K11-L12*Parameters!$B$6-IF($B12="Gather",Parameters!$B$17,0))) -> 100 | L12: =IF($K11<=0,0,MAX(0,IF($B12="Travel",Parameters!$B$13*7,IF($B12="Work",Parameters!$B$14,0))-(SUM(D11:J11)-SUM(D12:J12)))) -> 0 | M12: =IF(K12<=0,"RUN OVER","alive") -> alive
A13: 7 | B13: Work | C13: 7 | D13: =IF($K12<=0,D12,IF($B13="Travel",MAX(0,D12-Parameters!$B$13),IF(AND($B13="Work",$C13=1),MAX(0,D12-Parameters!$B$14),IF(AND($B13="Gather",$C13=1),MIN(Parameters!$B$10,D12+Parameters!$B$16),D12)))) -> 85 | E13: =IF($K12<=0,E12,IF($B13="Travel",MAX(0,E12-Parameters!$B$13),IF(AND($B13="Work",$C13=2),MAX(0,E12-Parameters!$B$14),IF(AND($B13="Gather",$C13=2),MIN(Parameters!$B$10,E12+Parameters!$B$16),E12)))) -> 85 | F13: =IF($K12<=0,F12,IF($B13="Travel",MAX(0,F12-Parameters!$B$13),IF(AND($B13="Work",$C13=3),MAX(0,F12-Parameters!$B$14),IF(AND($B13="Gather",$C13=3),MIN(Parameters!$B$10,F12+Parameters!$B$16),F12)))) -> 85 | G13: =IF($K12<=0,G12,IF($B13="Travel",MAX(0,G12-Parameters!$B$13),IF(AND($B13="Work",$C13=4),MAX(0,G12-Parameters!$B$14),IF(AND($B13="Gather",$C13=4),MIN(Parameters!$B$10,G12+Parameters!$B$16),G12)))) -> 85 | H13: =IF($K12<=0,H12,IF($B13="Travel",MAX(0,H12-Parameters!$B$13),IF(AND($B13="Work",$C13=5),MAX(0,H12-Parameters!$B$14),IF(AND($B13="Gather",$C13=5),MIN(Parameters!$B$10,H12+Parameters!$B$16),H12)))) -> 85 | I13: =IF($K12<=0,I12,IF($B13="Travel",MAX(0,I12-Parameters!$B$13),IF(AND($B13="Work",$C13=6),MAX(0,I12-Parameters!$B$14),IF(AND($B13="Gather",$C13=6),MIN(Parameters!$B$10,I12+Parameters!$B$16),I12)))) -> 85 | J13: =IF($K12<=0,J12,IF($B13="Travel",MAX(0,J12-Parameters!$B$13),IF(AND($B13="Work",$C13=7),MAX(0,J12-Parameters!$B$14),IF(AND($B13="Gather",$C13=7),MIN(Parameters!$B$10,J12+Parameters!$B$16),J12)))) -> 37 | K13: =IF($K12<=0,0,MAX(0,K12-L13*Parameters!$B$6-IF($B13="Gather",Parameters!$B$17,0))) -> 100 | L13: =IF($K12<=0,0,MAX(0,IF($B13="Travel",Parameters!$B$13*7,IF($B13="Work",Parameters!$B$14,0))-(SUM(D12:J12)-SUM(D13:J13)))) -> 0 | M13: =IF(K13<=0,"RUN OVER","alive") -> alive | O13: Edit column B and C to test a route.
A14: 8 | B14: Work | C14: 7 | D14: =IF($K13<=0,D13,IF($B14="Travel",MAX(0,D13-Parameters!$B$13),IF(AND($B14="Work",$C14=1),MAX(0,D13-Parameters!$B$14),IF(AND($B14="Gather",$C14=1),MIN(Parameters!$B$10,D13+Parameters!$B$16),D13)))) -> 85 | E14: =IF($K13<=0,E13,IF($B14="Travel",MAX(0,E13-Parameters!$B$13),IF(AND($B14="Work",$C14=2),MAX(0,E13-Parameters!$B$14),IF(AND($B14="Gather",$C14=2),MIN(Parameters!$B$10,E13+Parameters!$B$16),E13)))) -> 85 | F14: =IF($K13<=0,F13,IF($B14="Travel",MAX(0,F13-Parameters!$B$13),IF(AND($B14="Work",$C14=3),MAX(0,F13-Parameters!$B$14),IF(AND($B14="Gather",$C14=3),MIN(Parameters!$B$10,F13+Parameters!$B$16),F13)))) -> 85 | G14: =IF($K13<=0,G13,IF($B14="Travel",MAX(0,G13-Parameters!$B$13),IF(AND($B14="Work",$C14=4),MAX(0,G13-Parameters!$B$14),IF(AND($B14="Gather",$C14=4),MIN(Parameters!$B$10,G13+Parameters!$B$16),G13)))) -> 85 | H14: =IF($K13<=0,H13,IF($B14="Travel",MAX(0,H13-Parameters!$B$13),IF(AND($B14="Work",$C14=5),MAX(0,H13-Parameters!$B$14),IF(AND($B14="Gather",$C14=5),MIN(Parameters!$B$10,H13+Parameters!$B$16),H13)))) -> 85 | I14: =IF($K13<=0,I13,IF($B14="Travel",MAX(0,I13-Parameters!$B$13),IF(AND($B14="Work",$C14=6),MAX(0,I13-Parameters!$B$14),IF(AND($B14="Gather",$C14=6),MIN(Parameters!$B$10,I13+Parameters!$B$16),I13)))) -> 85 | J14: =IF($K13<=0,J13,IF($B14="Travel",MAX(0,J13-Parameters!$B$13),IF(AND($B14="Work",$C14=7),MAX(0,J13-Parameters!$B$14),IF(AND($B14="Gather",$C14=7),MIN(Parameters!$B$10,J13+Parameters!$B$16),J13)))) -> 29 | K14: =IF($K13<=0,0,MAX(0,K13-L14*Parameters!$B$6-IF($B14="Gather",Parameters!$B$17,0))) -> 100 | L14: =IF($K13<=0,0,MAX(0,IF($B14="Travel",Parameters!$B$13*7,IF($B14="Work",Parameters!$B$14,0))-(SUM(D13:J13)-SUM(D14:J14)))) -> 0 | M14: =IF(K14<=0,"RUN OVER","alive") -> alive | O14: Actions after RUN OVER are not counted.
A15: 9 | B15: Work | C15: 7 | D15: =IF($K14<=0,D14,IF($B15="Travel",MAX(0,D14-Parameters!$B$13),IF(AND($B15="Work",$C15=1),MAX(0,D14-Parameters!$B$14),IF(AND($B15="Gather",$C15=1),MIN(Parameters!$B$10,D14+Parameters!$B$16),D14)))) -> 85 | E15: =IF($K14<=0,E14,IF($B15="Travel",MAX(0,E14-Parameters!$B$13),IF(AND($B15="Work",$C15=2),MAX(0,E14-Parameters!$B$14),IF(AND($B15="Gather",$C15=2),MIN(Parameters!$B$10,E14+Parameters!$B$16),E14)))) -> 85 | F15: =IF($K14<=0,F14,IF($B15="Travel",MAX(0,F14-Parameters!$B$13),IF(AND($B15="Work",$C15=3),MAX(0,F14-Parameters!$B$14),IF(AND($B15="Gather",$C15=3),MIN(Parameters!$B$10,F14+Parameters!$B$16),F14)))) -> 85 | G15: =IF($K14<=0,G14,IF($B15="Travel",MAX(0,G14-Parameters!$B$13),IF(AND($B15="Work",$C15=4),MAX(0,G14-Parameters!$B$14),IF(AND($B15="Gather",$C15=4),MIN(Parameters!$B$10,G14+Parameters!$B$16),G14)))) -> 85 | H15: =IF($K14<=0,H14,IF($B15="Travel",MAX(0,H14-Parameters!$B$13),IF(AND($B15="Work",$C15=5),MAX(0,H14-Parameters!$B$14),IF(AND($B15="Gather",$C15=5),MIN(Parameters!$B$10,H14+Parameters!$B$16),H14)))) -> 85 | I15: =IF($K14<=0,I14,IF($B15="Travel",MAX(0,I14-Parameters!$B$13),IF(AND($B15="Work",$C15=6),MAX(0,I14-Parameters!$B$14),IF(AND($B15="Gather",$C15=6),MIN(Parameters!$B$10,I14+Parameters!$B$16),I14)))) -> 85 | J15: =IF($K14<=0,J14,IF($B15="Travel",MAX(0,J14-Parameters!$B$13),IF(AND($B15="Work",$C15=7),MAX(0,J14-Parameters!$B$14),IF(AND($B15="Gather",$C15=7),MIN(Parameters!$B$10,J14+Parameters!$B$16),J14)))) -> 21 | K15: =IF($K14<=0,0,MAX(0,K14-L15*Parameters!$B$6-IF($B15="Gather",Parameters!$B$17,0))) -> 100 | L15: =IF($K14<=0,0,MAX(0,IF($B15="Travel",Parameters!$B$13*7,IF($B15="Work",Parameters!$B$14,0))-(SUM(D14:J14)-SUM(D15:J15)))) -> 0 | M15: =IF(K15<=0,"RUN OVER","alive") -> alive
A16: 10 | B16: Work | C16: 7 | D16: =IF($K15<=0,D15,IF($B16="Travel",MAX(0,D15-Parameters!$B$13),IF(AND($B16="Work",$C16=1),MAX(0,D15-Parameters!$B$14),IF(AND($B16="Gather",$C16=1),MIN(Parameters!$B$10,D15+Parameters!$B$16),D15)))) -> 85 | E16: =IF($K15<=0,E15,IF($B16="Travel",MAX(0,E15-Parameters!$B$13),IF(AND($B16="Work",$C16=2),MAX(0,E15-Parameters!$B$14),IF(AND($B16="Gather",$C16=2),MIN(Parameters!$B$10,E15+Parameters!$B$16),E15)))) -> 85 | F16: =IF($K15<=0,F15,IF($B16="Travel",MAX(0,F15-Parameters!$B$13),IF(AND($B16="Work",$C16=3),MAX(0,F15-Parameters!$B$14),IF(AND($B16="Gather",$C16=3),MIN(Parameters!$B$10,F15+Parameters!$B$16),F15)))) -> 85 | G16: =IF($K15<=0,G15,IF($B16="Travel",MAX(0,G15-Parameters!$B$13),IF(AND($B16="Work",$C16=4),MAX(0,G15-Parameters!$B$14),IF(AND($B16="Gather",$C16=4),MIN(Parameters!$B$10,G15+Parameters!$B$16),G15)))) -> 85 | H16: =IF($K15<=0,H15,IF($B16="Travel",MAX(0,H15-Parameters!$B$13),IF(AND($B16="Work",$C16=5),MAX(0,H15-Parameters!$B$14),IF(AND($B16="Gather",$C16=5),MIN(Parameters!$B$10,H15+Parameters!$B$16),H15)))) -> 85 | I16: =IF($K15<=0,I15,IF($B16="Travel",MAX(0,I15-Parameters!$B$13),IF(AND($B16="Work",$C16=6),MAX(0,I15-Parameters!$B$14),IF(AND($B16="Gather",$C16=6),MIN(Parameters!$B$10,I15+Parameters!$B$16),I15)))) -> 85 | J16: =IF($K15<=0,J15,IF($B16="Travel",MAX(0,J15-Parameters!$B$13),IF(AND($B16="Work",$C16=7),MAX(0,J15-Parameters!$B$14),IF(AND($B16="Gather",$C16=7),MIN(Parameters!$B$10,J15+Parameters!$B$16),J15)))) -> 13 | K16: =IF($K15<=0,0,MAX(0,K15-L16*Parameters!$B$6-IF($B16="Gather",Parameters!$B$17,0))) -> 100 | L16: =IF($K15<=0,0,MAX(0,IF($B16="Travel",Parameters!$B$13*7,IF($B16="Work",Parameters!$B$14,0))-(SUM(D15:J15)-SUM(D16:J16)))) -> 0 | M16: =IF(K16<=0,"RUN OVER","alive") -> alive
A17: 11 | B17: Work | C17: 7 | D17: =IF($K16<=0,D16,IF($B17="Travel",MAX(0,D16-Parameters!$B$13),IF(AND($B17="Work",$C17=1),MAX(0,D16-Parameters!$B$14),IF(AND($B17="Gather",$C17=1),MIN(Parameters!$B$10,D16+Parameters!$B$16),D16)))) -> 85 | E17: =IF($K16<=0,E16,IF($B17="Travel",MAX(0,E16-Parameters!$B$13),IF(AND($B17="Work",$C17=2),MAX(0,E16-Parameters!$B$14),IF(AND($B17="Gather",$C17=2),MIN(Parameters!$B$10,E16+Parameters!$B$16),E16)))) -> 85 | F17: =IF($K16<=0,F16,IF($B17="Travel",MAX(0,F16-Parameters!$B$13),IF(AND($B17="Work",$C17=3),MAX(0,F16-Parameters!$B$14),IF(AND($B17="Gather",$C17=3),MIN(Parameters!$B$10,F16+Parameters!$B$16),F16)))) -> 85 | G17: =IF($K16<=0,G16,IF($B17="Travel",MAX(0,G16-Parameters!$B$13),IF(AND($B17="Work",$C17=4),MAX(0,G16-Parameters!$B$14),IF(AND($B17="Gather",$C17=4),MIN(Parameters!$B$10,G16+Parameters!$B$16),G16)))) -> 85 | H17: =IF($K16<=0,H16,IF($B17="Travel",MAX(0,H16-Parameters!$B$13),IF(AND($B17="Work",$C17=5),MAX(0,H16-Parameters!$B$14),IF(AND($B17="Gather",$C17=5),MIN(Parameters!$B$10,H16+Parameters!$B$16),H16)))) -> 85 | I17: =IF($K16<=0,I16,IF($B17="Travel",MAX(0,I16-Parameters!$B$13),IF(AND($B17="Work",$C17=6),MAX(0,I16-Parameters!$B$14),IF(AND($B17="Gather",$C17=6),MIN(Parameters!$B$10,I16+Parameters!$B$16),I16)))) -> 85 | J17: =IF($K16<=0,J16,IF($B17="Travel",MAX(0,J16-Parameters!$B$13),IF(AND($B17="Work",$C17=7),MAX(0,J16-Parameters!$B$14),IF(AND($B17="Gather",$C17=7),MIN(Parameters!$B$10,J16+Parameters!$B$16),J16)))) -> 5 | K17: =IF($K16<=0,0,MAX(0,K16-L17*Parameters!$B$6-IF($B17="Gather",Parameters!$B$17,0))) -> 100 | L17: =IF($K16<=0,0,MAX(0,IF($B17="Travel",Parameters!$B$13*7,IF($B17="Work",Parameters!$B$14,0))-(SUM(D16:J16)-SUM(D17:J17)))) -> 0 | M17: =IF(K17<=0,"RUN OVER","alive") -> alive
A18: 12 | B18: Work | C18: 7 | D18: =IF($K17<=0,D17,IF($B18="Travel",MAX(0,D17-Parameters!$B$13),IF(AND($B18="Work",$C18=1),MAX(0,D17-Parameters!$B$14),IF(AND($B18="Gather",$C18=1),MIN(Parameters!$B$10,D17+Parameters!$B$16),D17)))) -> 85 | E18: =IF($K17<=0,E17,IF($B18="Travel",MAX(0,E17-Parameters!$B$13),IF(AND($B18="Work",$C18=2),MAX(0,E17-Parameters!$B$14),IF(AND($B18="Gather",$C18=2),MIN(Parameters!$B$10,E17+Parameters!$B$16),E17)))) -> 85 | F18: =IF($K17<=0,F17,IF($B18="Travel",MAX(0,F17-Parameters!$B$13),IF(AND($B18="Work",$C18=3),MAX(0,F17-Parameters!$B$14),IF(AND($B18="Gather",$C18=3),MIN(Parameters!$B$10,F17+Parameters!$B$16),F17)))) -> 85 | G18: =IF($K17<=0,G17,IF($B18="Travel",MAX(0,G17-Parameters!$B$13),IF(AND($B18="Work",$C18=4),MAX(0,G17-Parameters!$B$14),IF(AND($B18="Gather",$C18=4),MIN(Parameters!$B$10,G17+Parameters!$B$16),G17)))) -> 85 | H18: =IF($K17<=0,H17,IF($B18="Travel",MAX(0,H17-Parameters!$B$13),IF(AND($B18="Work",$C18=5),MAX(0,H17-Parameters!$B$14),IF(AND($B18="Gather",$C18=5),MIN(Parameters!$B$10,H17+Parameters!$B$16),H17)))) -> 85 | I18: =IF($K17<=0,I17,IF($B18="Travel",MAX(0,I17-Parameters!$B$13),IF(AND($B18="Work",$C18=6),MAX(0,I17-Parameters!$B$14),IF(AND($B18="Gather",$C18=6),MIN(Parameters!$B$10,I17+Parameters!$B$16),I17)))) -> 85 | J18: =IF($K17<=0,J17,IF($B18="Travel",MAX(0,J17-Parameters!$B$13),IF(AND($B18="Work",$C18=7),MAX(0,J17-Parameters!$B$14),IF(AND($B18="Gather",$C18=7),MIN(Parameters!$B$10,J17+Parameters!$B$16),J17)))) -> 0 | K18: =IF($K17<=0,0,MAX(0,K17-L18*Parameters!$B$6-IF($B18="Gather",Parameters!$B$17,0))) -> 97 | L18: =IF($K17<=0,0,MAX(0,IF($B18="Travel",Parameters!$B$13*7,IF($B18="Work",Parameters!$B$14,0))-(SUM(D17:J17)-SUM(D18:J18)))) -> 3 | M18: =IF(K18<=0,"RUN OVER","alive") -> alive
A19: 13 | B19: Work | C19: 7 | D19: =IF($K18<=0,D18,IF($B19="Travel",MAX(0,D18-Parameters!$B$13),IF(AND($B19="Work",$C19=1),MAX(0,D18-Parameters!$B$14),IF(AND($B19="Gather",$C19=1),MIN(Parameters!$B$10,D18+Parameters!$B$16),D18)))) -> 85 | E19: =IF($K18<=0,E18,IF($B19="Travel",MAX(0,E18-Parameters!$B$13),IF(AND($B19="Work",$C19=2),MAX(0,E18-Parameters!$B$14),IF(AND($B19="Gather",$C19=2),MIN(Parameters!$B$10,E18+Parameters!$B$16),E18)))) -> 85 | F19: =IF($K18<=0,F18,IF($B19="Travel",MAX(0,F18-Parameters!$B$13),IF(AND($B19="Work",$C19=3),MAX(0,F18-Parameters!$B$14),IF(AND($B19="Gather",$C19=3),MIN(Parameters!$B$10,F18+Parameters!$B$16),F18)))) -> 85 | G19: =IF($K18<=0,G18,IF($B19="Travel",MAX(0,G18-Parameters!$B$13),IF(AND($B19="Work",$C19=4),MAX(0,G18-Parameters!$B$14),IF(AND($B19="Gather",$C19=4),MIN(Parameters!$B$10,G18+Parameters!$B$16),G18)))) -> 85 | H19: =IF($K18<=0,H18,IF($B19="Travel",MAX(0,H18-Parameters!$B$13),IF(AND($B19="Work",$C19=5),MAX(0,H18-Parameters!$B$14),IF(AND($B19="Gather",$C19=5),MIN(Parameters!$B$10,H18+Parameters!$B$16),H18)))) -> 85 | I19: =IF($K18<=0,I18,IF($B19="Travel",MAX(0,I18-Parameters!$B$13),IF(AND($B19="Work",$C19=6),MAX(0,I18-Parameters!$B$14),IF(AND($B19="Gather",$C19=6),MIN(Parameters!$B$10,I18+Parameters!$B$16),I18)))) -> 85 | J19: =IF($K18<=0,J18,IF($B19="Travel",MAX(0,J18-Parameters!$B$13),IF(AND($B19="Work",$C19=7),MAX(0,J18-Parameters!$B$14),IF(AND($B19="Gather",$C19=7),MIN(Parameters!$B$10,J18+Parameters!$B$16),J18)))) -> 0 | K19: =IF($K18<=0,0,MAX(0,K18-L19*Parameters!$B$6-IF($B19="Gather",Parameters!$B$17,0))) -> 89 | L19: =IF($K18<=0,0,MAX(0,IF($B19="Travel",Parameters!$B$13*7,IF($B19="Work",Parameters!$B$14,0))-(SUM(D18:J18)-SUM(D19:J19)))) -> 8 | M19: =IF(K19<=0,"RUN OVER","alive") -> alive
A20: 14 | B20: Gather | C20: 7 | D20: =IF($K19<=0,D19,IF($B20="Travel",MAX(0,D19-Parameters!$B$13),IF(AND($B20="Work",$C20=1),MAX(0,D19-Parameters!$B$14),IF(AND($B20="Gather",$C20=1),MIN(Parameters!$B$10,D19+Parameters!$B$16),D19)))) -> 85 | E20: =IF($K19<=0,E19,IF($B20="Travel",MAX(0,E19-Parameters!$B$13),IF(AND($B20="Work",$C20=2),MAX(0,E19-Parameters!$B$14),IF(AND($B20="Gather",$C20=2),MIN(Parameters!$B$10,E19+Parameters!$B$16),E19)))) -> 85 | F20: =IF($K19<=0,F19,IF($B20="Travel",MAX(0,F19-Parameters!$B$13),IF(AND($B20="Work",$C20=3),MAX(0,F19-Parameters!$B$14),IF(AND($B20="Gather",$C20=3),MIN(Parameters!$B$10,F19+Parameters!$B$16),F19)))) -> 85 | G20: =IF($K19<=0,G19,IF($B20="Travel",MAX(0,G19-Parameters!$B$13),IF(AND($B20="Work",$C20=4),MAX(0,G19-Parameters!$B$14),IF(AND($B20="Gather",$C20=4),MIN(Parameters!$B$10,G19+Parameters!$B$16),G19)))) -> 85 | H20: =IF($K19<=0,H19,IF($B20="Travel",MAX(0,H19-Parameters!$B$13),IF(AND($B20="Work",$C20=5),MAX(0,H19-Parameters!$B$14),IF(AND($B20="Gather",$C20=5),MIN(Parameters!$B$10,H19+Parameters!$B$16),H19)))) -> 85 | I20: =IF($K19<=0,I19,IF($B20="Travel",MAX(0,I19-Parameters!$B$13),IF(AND($B20="Work",$C20=6),MAX(0,I19-Parameters!$B$14),IF(AND($B20="Gather",$C20=6),MIN(Parameters!$B$10,I19+Parameters!$B$16),I19)))) -> 85 | J20: =IF($K19<=0,J19,IF($B20="Travel",MAX(0,J19-Parameters!$B$13),IF(AND($B20="Work",$C20=7),MAX(0,J19-Parameters!$B$14),IF(AND($B20="Gather",$C20=7),MIN(Parameters!$B$10,J19+Parameters!$B$16),J19)))) -> 20 | K20: =IF($K19<=0,0,MAX(0,K19-L20*Parameters!$B$6-IF($B20="Gather",Parameters!$B$17,0))) -> 67 | L20: =IF($K19<=0,0,MAX(0,IF($B20="Travel",Parameters!$B$13*7,IF($B20="Work",Parameters!$B$14,0))-(SUM(D19:J19)-SUM(D20:J20)))) -> 20 | M20: =IF(K20<=0,"RUN OVER","alive") -> alive
A21: 15 | B21: Gather | C21: 7 | D21: =IF($K20<=0,D20,IF($B21="Travel",MAX(0,D20-Parameters!$B$13),IF(AND($B21="Work",$C21=1),MAX(0,D20-Parameters!$B$14),IF(AND($B21="Gather",$C21=1),MIN(Parameters!$B$10,D20+Parameters!$B$16),D20)))) -> 85 | E21: =IF($K20<=0,E20,IF($B21="Travel",MAX(0,E20-Parameters!$B$13),IF(AND($B21="Work",$C21=2),MAX(0,E20-Parameters!$B$14),IF(AND($B21="Gather",$C21=2),MIN(Parameters!$B$10,E20+Parameters!$B$16),E20)))) -> 85 | F21: =IF($K20<=0,F20,IF($B21="Travel",MAX(0,F20-Parameters!$B$13),IF(AND($B21="Work",$C21=3),MAX(0,F20-Parameters!$B$14),IF(AND($B21="Gather",$C21=3),MIN(Parameters!$B$10,F20+Parameters!$B$16),F20)))) -> 85 | G21: =IF($K20<=0,G20,IF($B21="Travel",MAX(0,G20-Parameters!$B$13),IF(AND($B21="Work",$C21=4),MAX(0,G20-Parameters!$B$14),IF(AND($B21="Gather",$C21=4),MIN(Parameters!$B$10,G20+Parameters!$B$16),G20)))) -> 85 | H21: =IF($K20<=0,H20,IF($B21="Travel",MAX(0,H20-Parameters!$B$13),IF(AND($B21="Work",$C21=5),MAX(0,H20-Parameters!$B$14),IF(AND($B21="Gather",$C21=5),MIN(Parameters!$B$10,H20+Parameters!$B$16),H20)))) -> 85 | I21: =IF($K20<=0,I20,IF($B21="Travel",MAX(0,I20-Parameters!$B$13),IF(AND($B21="Work",$C21=6),MAX(0,I20-Parameters!$B$14),IF(AND($B21="Gather",$C21=6),MIN(Parameters!$B$10,I20+Parameters!$B$16),I20)))) -> 85 | J21: =IF($K20<=0,J20,IF($B21="Travel",MAX(0,J20-Parameters!$B$13),IF(AND($B21="Work",$C21=7),MAX(0,J20-Parameters!$B$14),IF(AND($B21="Gather",$C21=7),MIN(Parameters!$B$10,J20+Parameters!$B$16),J20)))) -> 40 | K21: =IF($K20<=0,0,MAX(0,K20-L21*Parameters!$B$6-IF($B21="Gather",Parameters!$B$17,0))) -> 45 | L21: =IF($K20<=0,0,MAX(0,IF($B21="Travel",Parameters!$B$13*7,IF($B21="Work",Parameters!$B$14,0))-(SUM(D20:J20)-SUM(D21:J21)))) -> 20 | M21: =IF(K21<=0,"RUN OVER","alive") -> alive
A22: 16 | B22: Travel | D22: =IF($K21<=0,D21,IF($B22="Travel",MAX(0,D21-Parameters!$B$13),IF(AND($B22="Work",$C22=1),MAX(0,D21-Parameters!$B$14),IF(AND($B22="Gather",$C22=1),MIN(Parameters!$B$10,D21+Parameters!$B$16),D21)))) -> 70 | E22: =IF($K21<=0,E21,IF($B22="Travel",MAX(0,E21-Parameters!$B$13),IF(AND($B22="Work",$C22=2),MAX(0,E21-Parameters!$B$14),IF(AND($B22="Gather",$C22=2),MIN(Parameters!$B$10,E21+Parameters!$B$16),E21)))) -> 70 | F22: =IF($K21<=0,F21,IF($B22="Travel",MAX(0,F21-Parameters!$B$13),IF(AND($B22="Work",$C22=3),MAX(0,F21-Parameters!$B$14),IF(AND($B22="Gather",$C22=3),MIN(Parameters!$B$10,F21+Parameters!$B$16),F21)))) -> 70 | G22: =IF($K21<=0,G21,IF($B22="Travel",MAX(0,G21-Parameters!$B$13),IF(AND($B22="Work",$C22=4),MAX(0,G21-Parameters!$B$14),IF(AND($B22="Gather",$C22=4),MIN(Parameters!$B$10,G21+Parameters!$B$16),G21)))) -> 70 | H22: =IF($K21<=0,H21,IF($B22="Travel",MAX(0,H21-Parameters!$B$13),IF(AND($B22="Work",$C22=5),MAX(0,H21-Parameters!$B$14),IF(AND($B22="Gather",$C22=5),MIN(Parameters!$B$10,H21+Parameters!$B$16),H21)))) -> 70 | I22: =IF($K21<=0,I21,IF($B22="Travel",MAX(0,I21-Parameters!$B$13),IF(AND($B22="Work",$C22=6),MAX(0,I21-Parameters!$B$14),IF(AND($B22="Gather",$C22=6),MIN(Parameters!$B$10,I21+Parameters!$B$16),I21)))) -> 70 | J22: =IF($K21<=0,J21,IF($B22="Travel",MAX(0,J21-Parameters!$B$13),IF(AND($B22="Work",$C22=7),MAX(0,J21-Parameters!$B$14),IF(AND($B22="Gather",$C22=7),MIN(Parameters!$B$10,J21+Parameters!$B$16),J21)))) -> 25 | K22: =IF($K21<=0,0,MAX(0,K21-L22*Parameters!$B$6-IF($B22="Gather",Parameters!$B$17,0))) -> 45 | L22: =IF($K21<=0,0,MAX(0,IF($B22="Travel",Parameters!$B$13*7,IF($B22="Work",Parameters!$B$14,0))-(SUM(D21:J21)-SUM(D22:J22)))) -> 0 | M22: =IF(K22<=0,"RUN OVER","alive") -> alive
A23: 17 | B23: Work | C23: 1 | D23: =IF($K22<=0,D22,IF($B23="Travel",MAX(0,D22-Parameters!$B$13),IF(AND($B23="Work",$C23=1),MAX(0,D22-Parameters!$B$14),IF(AND($B23="Gather",$C23=1),MIN(Parameters!$B$10,D22+Parameters!$B$16),D22)))) -> 62 | E23: =IF($K22<=0,E22,IF($B23="Travel",MAX(0,E22-Parameters!$B$13),IF(AND($B23="Work",$C23=2),MAX(0,E22-Parameters!$B$14),IF(AND($B23="Gather",$C23=2),MIN(Parameters!$B$10,E22+Parameters!$B$16),E22)))) -> 70 | F23: =IF($K22<=0,F22,IF($B23="Travel",MAX(0,F22-Parameters!$B$13),IF(AND($B23="Work",$C23=3),MAX(0,F22-Parameters!$B$14),IF(AND($B23="Gather",$C23=3),MIN(Parameters!$B$10,F22+Parameters!$B$16),F22)))) -> 70 | G23: =IF($K22<=0,G22,IF($B23="Travel",MAX(0,G22-Parameters!$B$13),IF(AND($B23="Work",$C23=4),MAX(0,G22-Parameters!$B$14),IF(AND($B23="Gather",$C23=4),MIN(Parameters!$B$10,G22+Parameters!$B$16),G22)))) -> 70 | H23: =IF($K22<=0,H22,IF($B23="Travel",MAX(0,H22-Parameters!$B$13),IF(AND($B23="Work",$C23=5),MAX(0,H22-Parameters!$B$14),IF(AND($B23="Gather",$C23=5),MIN(Parameters!$B$10,H22+Parameters!$B$16),H22)))) -> 70 | I23: =IF($K22<=0,I22,IF($B23="Travel",MAX(0,I22-Parameters!$B$13),IF(AND($B23="Work",$C23=6),MAX(0,I22-Parameters!$B$14),IF(AND($B23="Gather",$C23=6),MIN(Parameters!$B$10,I22+Parameters!$B$16),I22)))) -> 70 | J23: =IF($K22<=0,J22,IF($B23="Travel",MAX(0,J22-Parameters!$B$13),IF(AND($B23="Work",$C23=7),MAX(0,J22-Parameters!$B$14),IF(AND($B23="Gather",$C23=7),MIN(Parameters!$B$10,J22+Parameters!$B$16),J22)))) -> 25 | K23: =IF($K22<=0,0,MAX(0,K22-L23*Parameters!$B$6-IF($B23="Gather",Parameters!$B$17,0))) -> 45 | L23: =IF($K22<=0,0,MAX(0,IF($B23="Travel",Parameters!$B$13*7,IF($B23="Work",Parameters!$B$14,0))-(SUM(D22:J22)-SUM(D23:J23)))) -> 0 | M23: =IF(K23<=0,"RUN OVER","alive") -> alive
A24: 18 | B24: Work | C24: 1 | D24: =IF($K23<=0,D23,IF($B24="Travel",MAX(0,D23-Parameters!$B$13),IF(AND($B24="Work",$C24=1),MAX(0,D23-Parameters!$B$14),IF(AND($B24="Gather",$C24=1),MIN(Parameters!$B$10,D23+Parameters!$B$16),D23)))) -> 54 | E24: =IF($K23<=0,E23,IF($B24="Travel",MAX(0,E23-Parameters!$B$13),IF(AND($B24="Work",$C24=2),MAX(0,E23-Parameters!$B$14),IF(AND($B24="Gather",$C24=2),MIN(Parameters!$B$10,E23+Parameters!$B$16),E23)))) -> 70 | F24: =IF($K23<=0,F23,IF($B24="Travel",MAX(0,F23-Parameters!$B$13),IF(AND($B24="Work",$C24=3),MAX(0,F23-Parameters!$B$14),IF(AND($B24="Gather",$C24=3),MIN(Parameters!$B$10,F23+Parameters!$B$16),F23)))) -> 70 | G24: =IF($K23<=0,G23,IF($B24="Travel",MAX(0,G23-Parameters!$B$13),IF(AND($B24="Work",$C24=4),MAX(0,G23-Parameters!$B$14),IF(AND($B24="Gather",$C24=4),MIN(Parameters!$B$10,G23+Parameters!$B$16),G23)))) -> 70 | H24: =IF($K23<=0,H23,IF($B24="Travel",MAX(0,H23-Parameters!$B$13),IF(AND($B24="Work",$C24=5),MAX(0,H23-Parameters!$B$14),IF(AND($B24="Gather",$C24=5),MIN(Parameters!$B$10,H23+Parameters!$B$16),H23)))) -> 70 | I24: =IF($K23<=0,I23,IF($B24="Travel",MAX(0,I23-Parameters!$B$13),IF(AND($B24="Work",$C24=6),MAX(0,I23-Parameters!$B$14),IF(AND($B24="Gather",$C24=6),MIN(Parameters!$B$10,I23+Parameters!$B$16),I23)))) -> 70 | J24: =IF($K23<=0,J23,IF($B24="Travel",MAX(0,J23-Parameters!$B$13),IF(AND($B24="Work",$C24=7),MAX(0,J23-Parameters!$B$14),IF(AND($B24="Gather",$C24=7),MIN(Parameters!$B$10,J23+Parameters!$B$16),J23)))) -> 25 | K24: =IF($K23<=0,0,MAX(0,K23-L24*Parameters!$B$6-IF($B24="Gather",Parameters!$B$17,0))) -> 45 | L24: =IF($K23<=0,0,MAX(0,IF($B24="Travel",Parameters!$B$13*7,IF($B24="Work",Parameters!$B$14,0))-(SUM(D23:J23)-SUM(D24:J24)))) -> 0 | M24: =IF(K24<=0,"RUN OVER","alive") -> alive
A25: 19 | B25: Work | C25: 1 | D25: =IF($K24<=0,D24,IF($B25="Travel",MAX(0,D24-Parameters!$B$13),IF(AND($B25="Work",$C25=1),MAX(0,D24-Parameters!$B$14),IF(AND($B25="Gather",$C25=1),MIN(Parameters!$B$10,D24+Parameters!$B$16),D24)))) -> 46 | E25: =IF($K24<=0,E24,IF($B25="Travel",MAX(0,E24-Parameters!$B$13),IF(AND($B25="Work",$C25=2),MAX(0,E24-Parameters!$B$14),IF(AND($B25="Gather",$C25=2),MIN(Parameters!$B$10,E24+Parameters!$B$16),E24)))) -> 70 | F25: =IF($K24<=0,F24,IF($B25="Travel",MAX(0,F24-Parameters!$B$13),IF(AND($B25="Work",$C25=3),MAX(0,F24-Parameters!$B$14),IF(AND($B25="Gather",$C25=3),MIN(Parameters!$B$10,F24+Parameters!$B$16),F24)))) -> 70 | G25: =IF($K24<=0,G24,IF($B25="Travel",MAX(0,G24-Parameters!$B$13),IF(AND($B25="Work",$C25=4),MAX(0,G24-Parameters!$B$14),IF(AND($B25="Gather",$C25=4),MIN(Parameters!$B$10,G24+Parameters!$B$16),G24)))) -> 70 | H25: =IF($K24<=0,H24,IF($B25="Travel",MAX(0,H24-Parameters!$B$13),IF(AND($B25="Work",$C25=5),MAX(0,H24-Parameters!$B$14),IF(AND($B25="Gather",$C25=5),MIN(Parameters!$B$10,H24+Parameters!$B$16),H24)))) -> 70 | I25: =IF($K24<=0,I24,IF($B25="Travel",MAX(0,I24-Parameters!$B$13),IF(AND($B25="Work",$C25=6),MAX(0,I24-Parameters!$B$14),IF(AND($B25="Gather",$C25=6),MIN(Parameters!$B$10,I24+Parameters!$B$16),I24)))) -> 70 | J25: =IF($K24<=0,J24,IF($B25="Travel",MAX(0,J24-Parameters!$B$13),IF(AND($B25="Work",$C25=7),MAX(0,J24-Parameters!$B$14),IF(AND($B25="Gather",$C25=7),MIN(Parameters!$B$10,J24+Parameters!$B$16),J24)))) -> 25 | K25: =IF($K24<=0,0,MAX(0,K24-L25*Parameters!$B$6-IF($B25="Gather",Parameters!$B$17,0))) -> 45 | L25: =IF($K24<=0,0,MAX(0,IF($B25="Travel",Parameters!$B$13*7,IF($B25="Work",Parameters!$B$14,0))-(SUM(D24:J24)-SUM(D25:J25)))) -> 0 | M25: =IF(K25<=0,"RUN OVER","alive") -> alive
A26: 20 | B26: Work | C26: 1 | D26: =IF($K25<=0,D25,IF($B26="Travel",MAX(0,D25-Parameters!$B$13),IF(AND($B26="Work",$C26=1),MAX(0,D25-Parameters!$B$14),IF(AND($B26="Gather",$C26=1),MIN(Parameters!$B$10,D25+Parameters!$B$16),D25)))) -> 38 | E26: =IF($K25<=0,E25,IF($B26="Travel",MAX(0,E25-Parameters!$B$13),IF(AND($B26="Work",$C26=2),MAX(0,E25-Parameters!$B$14),IF(AND($B26="Gather",$C26=2),MIN(Parameters!$B$10,E25+Parameters!$B$16),E25)))) -> 70 | F26: =IF($K25<=0,F25,IF($B26="Travel",MAX(0,F25-Parameters!$B$13),IF(AND($B26="Work",$C26=3),MAX(0,F25-Parameters!$B$14),IF(AND($B26="Gather",$C26=3),MIN(Parameters!$B$10,F25+Parameters!$B$16),F25)))) -> 70 | G26: =IF($K25<=0,G25,IF($B26="Travel",MAX(0,G25-Parameters!$B$13),IF(AND($B26="Work",$C26=4),MAX(0,G25-Parameters!$B$14),IF(AND($B26="Gather",$C26=4),MIN(Parameters!$B$10,G25+Parameters!$B$16),G25)))) -> 70 | H26: =IF($K25<=0,H25,IF($B26="Travel",MAX(0,H25-Parameters!$B$13),IF(AND($B26="Work",$C26=5),MAX(0,H25-Parameters!$B$14),IF(AND($B26="Gather",$C26=5),MIN(Parameters!$B$10,H25+Parameters!$B$16),H25)))) -> 70 | I26: =IF($K25<=0,I25,IF($B26="Travel",MAX(0,I25-Parameters!$B$13),IF(AND($B26="Work",$C26=6),MAX(0,I25-Parameters!$B$14),IF(AND($B26="Gather",$C26=6),MIN(Parameters!$B$10,I25+Parameters!$B$16),I25)))) -> 70 | J26: =IF($K25<=0,J25,IF($B26="Travel",MAX(0,J25-Parameters!$B$13),IF(AND($B26="Work",$C26=7),MAX(0,J25-Parameters!$B$14),IF(AND($B26="Gather",$C26=7),MIN(Parameters!$B$10,J25+Parameters!$B$16),J25)))) -> 25 | K26: =IF($K25<=0,0,MAX(0,K25-L26*Parameters!$B$6-IF($B26="Gather",Parameters!$B$17,0))) -> 45 | L26: =IF($K25<=0,0,MAX(0,IF($B26="Travel",Parameters!$B$13*7,IF($B26="Work",Parameters!$B$14,0))-(SUM(D25:J25)-SUM(D26:J26)))) -> 0 | M26: =IF(K26<=0,"RUN OVER","alive") -> alive
A27: 21 | B27: Work | C27: 1 | D27: =IF($K26<=0,D26,IF($B27="Travel",MAX(0,D26-Parameters!$B$13),IF(AND($B27="Work",$C27=1),MAX(0,D26-Parameters!$B$14),IF(AND($B27="Gather",$C27=1),MIN(Parameters!$B$10,D26+Parameters!$B$16),D26)))) -> 30 | E27: =IF($K26<=0,E26,IF($B27="Travel",MAX(0,E26-Parameters!$B$13),IF(AND($B27="Work",$C27=2),MAX(0,E26-Parameters!$B$14),IF(AND($B27="Gather",$C27=2),MIN(Parameters!$B$10,E26+Parameters!$B$16),E26)))) -> 70 | F27: =IF($K26<=0,F26,IF($B27="Travel",MAX(0,F26-Parameters!$B$13),IF(AND($B27="Work",$C27=3),MAX(0,F26-Parameters!$B$14),IF(AND($B27="Gather",$C27=3),MIN(Parameters!$B$10,F26+Parameters!$B$16),F26)))) -> 70 | G27: =IF($K26<=0,G26,IF($B27="Travel",MAX(0,G26-Parameters!$B$13),IF(AND($B27="Work",$C27=4),MAX(0,G26-Parameters!$B$14),IF(AND($B27="Gather",$C27=4),MIN(Parameters!$B$10,G26+Parameters!$B$16),G26)))) -> 70 | H27: =IF($K26<=0,H26,IF($B27="Travel",MAX(0,H26-Parameters!$B$13),IF(AND($B27="Work",$C27=5),MAX(0,H26-Parameters!$B$14),IF(AND($B27="Gather",$C27=5),MIN(Parameters!$B$10,H26+Parameters!$B$16),H26)))) -> 70 | I27: =IF($K26<=0,I26,IF($B27="Travel",MAX(0,I26-Parameters!$B$13),IF(AND($B27="Work",$C27=6),MAX(0,I26-Parameters!$B$14),IF(AND($B27="Gather",$C27=6),MIN(Parameters!$B$10,I26+Parameters!$B$16),I26)))) -> 70 | J27: =IF($K26<=0,J26,IF($B27="Travel",MAX(0,J26-Parameters!$B$13),IF(AND($B27="Work",$C27=7),MAX(0,J26-Parameters!$B$14),IF(AND($B27="Gather",$C27=7),MIN(Parameters!$B$10,J26+Parameters!$B$16),J26)))) -> 25 | K27: =IF($K26<=0,0,MAX(0,K26-L27*Parameters!$B$6-IF($B27="Gather",Parameters!$B$17,0))) -> 45 | L27: =IF($K26<=0,0,MAX(0,IF($B27="Travel",Parameters!$B$13*7,IF($B27="Work",Parameters!$B$14,0))-(SUM(D26:J26)-SUM(D27:J27)))) -> 0 | M27: =IF(K27<=0,"RUN OVER","alive") -> alive
A28: 22 | B28: Work | C28: 1 | D28: =IF($K27<=0,D27,IF($B28="Travel",MAX(0,D27-Parameters!$B$13),IF(AND($B28="Work",$C28=1),MAX(0,D27-Parameters!$B$14),IF(AND($B28="Gather",$C28=1),MIN(Parameters!$B$10,D27+Parameters!$B$16),D27)))) -> 22 | E28: =IF($K27<=0,E27,IF($B28="Travel",MAX(0,E27-Parameters!$B$13),IF(AND($B28="Work",$C28=2),MAX(0,E27-Parameters!$B$14),IF(AND($B28="Gather",$C28=2),MIN(Parameters!$B$10,E27+Parameters!$B$16),E27)))) -> 70 | F28: =IF($K27<=0,F27,IF($B28="Travel",MAX(0,F27-Parameters!$B$13),IF(AND($B28="Work",$C28=3),MAX(0,F27-Parameters!$B$14),IF(AND($B28="Gather",$C28=3),MIN(Parameters!$B$10,F27+Parameters!$B$16),F27)))) -> 70 | G28: =IF($K27<=0,G27,IF($B28="Travel",MAX(0,G27-Parameters!$B$13),IF(AND($B28="Work",$C28=4),MAX(0,G27-Parameters!$B$14),IF(AND($B28="Gather",$C28=4),MIN(Parameters!$B$10,G27+Parameters!$B$16),G27)))) -> 70 | H28: =IF($K27<=0,H27,IF($B28="Travel",MAX(0,H27-Parameters!$B$13),IF(AND($B28="Work",$C28=5),MAX(0,H27-Parameters!$B$14),IF(AND($B28="Gather",$C28=5),MIN(Parameters!$B$10,H27+Parameters!$B$16),H27)))) -> 70 | I28: =IF($K27<=0,I27,IF($B28="Travel",MAX(0,I27-Parameters!$B$13),IF(AND($B28="Work",$C28=6),MAX(0,I27-Parameters!$B$14),IF(AND($B28="Gather",$C28=6),MIN(Parameters!$B$10,I27+Parameters!$B$16),I27)))) -> 70 | J28: =IF($K27<=0,J27,IF($B28="Travel",MAX(0,J27-Parameters!$B$13),IF(AND($B28="Work",$C28=7),MAX(0,J27-Parameters!$B$14),IF(AND($B28="Gather",$C28=7),MIN(Parameters!$B$10,J27+Parameters!$B$16),J27)))) -> 25 | K28: =IF($K27<=0,0,MAX(0,K27-L28*Parameters!$B$6-IF($B28="Gather",Parameters!$B$17,0))) -> 45 | L28: =IF($K27<=0,0,MAX(0,IF($B28="Travel",Parameters!$B$13*7,IF($B28="Work",Parameters!$B$14,0))-(SUM(D27:J27)-SUM(D28:J28)))) -> 0 | M28: =IF(K28<=0,"RUN OVER","alive") -> alive
A29: 23 | B29: Work | C29: 1 | D29: =IF($K28<=0,D28,IF($B29="Travel",MAX(0,D28-Parameters!$B$13),IF(AND($B29="Work",$C29=1),MAX(0,D28-Parameters!$B$14),IF(AND($B29="Gather",$C29=1),MIN(Parameters!$B$10,D28+Parameters!$B$16),D28)))) -> 14 | E29: =IF($K28<=0,E28,IF($B29="Travel",MAX(0,E28-Parameters!$B$13),IF(AND($B29="Work",$C29=2),MAX(0,E28-Parameters!$B$14),IF(AND($B29="Gather",$C29=2),MIN(Parameters!$B$10,E28+Parameters!$B$16),E28)))) -> 70 | F29: =IF($K28<=0,F28,IF($B29="Travel",MAX(0,F28-Parameters!$B$13),IF(AND($B29="Work",$C29=3),MAX(0,F28-Parameters!$B$14),IF(AND($B29="Gather",$C29=3),MIN(Parameters!$B$10,F28+Parameters!$B$16),F28)))) -> 70 | G29: =IF($K28<=0,G28,IF($B29="Travel",MAX(0,G28-Parameters!$B$13),IF(AND($B29="Work",$C29=4),MAX(0,G28-Parameters!$B$14),IF(AND($B29="Gather",$C29=4),MIN(Parameters!$B$10,G28+Parameters!$B$16),G28)))) -> 70 | H29: =IF($K28<=0,H28,IF($B29="Travel",MAX(0,H28-Parameters!$B$13),IF(AND($B29="Work",$C29=5),MAX(0,H28-Parameters!$B$14),IF(AND($B29="Gather",$C29=5),MIN(Parameters!$B$10,H28+Parameters!$B$16),H28)))) -> 70 | I29: =IF($K28<=0,I28,IF($B29="Travel",MAX(0,I28-Parameters!$B$13),IF(AND($B29="Work",$C29=6),MAX(0,I28-Parameters!$B$14),IF(AND($B29="Gather",$C29=6),MIN(Parameters!$B$10,I28+Parameters!$B$16),I28)))) -> 70 | J29: =IF($K28<=0,J28,IF($B29="Travel",MAX(0,J28-Parameters!$B$13),IF(AND($B29="Work",$C29=7),MAX(0,J28-Parameters!$B$14),IF(AND($B29="Gather",$C29=7),MIN(Parameters!$B$10,J28+Parameters!$B$16),J28)))) -> 25 | K29: =IF($K28<=0,0,MAX(0,K28-L29*Parameters!$B$6-IF($B29="Gather",Parameters!$B$17,0))) -> 45 | L29: =IF($K28<=0,0,MAX(0,IF($B29="Travel",Parameters!$B$13*7,IF($B29="Work",Parameters!$B$14,0))-(SUM(D28:J28)-SUM(D29:J29)))) -> 0 | M29: =IF(K29<=0,"RUN OVER","alive") -> alive
A30: 24 | B30: Work | C30: 1 | D30: =IF($K29<=0,D29,IF($B30="Travel",MAX(0,D29-Parameters!$B$13),IF(AND($B30="Work",$C30=1),MAX(0,D29-Parameters!$B$14),IF(AND($B30="Gather",$C30=1),MIN(Parameters!$B$10,D29+Parameters!$B$16),D29)))) -> 6 | E30: =IF($K29<=0,E29,IF($B30="Travel",MAX(0,E29-Parameters!$B$13),IF(AND($B30="Work",$C30=2),MAX(0,E29-Parameters!$B$14),IF(AND($B30="Gather",$C30=2),MIN(Parameters!$B$10,E29+Parameters!$B$16),E29)))) -> 70 | F30: =IF($K29<=0,F29,IF($B30="Travel",MAX(0,F29-Parameters!$B$13),IF(AND($B30="Work",$C30=3),MAX(0,F29-Parameters!$B$14),IF(AND($B30="Gather",$C30=3),MIN(Parameters!$B$10,F29+Parameters!$B$16),F29)))) -> 70 | G30: =IF($K29<=0,G29,IF($B30="Travel",MAX(0,G29-Parameters!$B$13),IF(AND($B30="Work",$C30=4),MAX(0,G29-Parameters!$B$14),IF(AND($B30="Gather",$C30=4),MIN(Parameters!$B$10,G29+Parameters!$B$16),G29)))) -> 70 | H30: =IF($K29<=0,H29,IF($B30="Travel",MAX(0,H29-Parameters!$B$13),IF(AND($B30="Work",$C30=5),MAX(0,H29-Parameters!$B$14),IF(AND($B30="Gather",$C30=5),MIN(Parameters!$B$10,H29+Parameters!$B$16),H29)))) -> 70 | I30: =IF($K29<=0,I29,IF($B30="Travel",MAX(0,I29-Parameters!$B$13),IF(AND($B30="Work",$C30=6),MAX(0,I29-Parameters!$B$14),IF(AND($B30="Gather",$C30=6),MIN(Parameters!$B$10,I29+Parameters!$B$16),I29)))) -> 70 | J30: =IF($K29<=0,J29,IF($B30="Travel",MAX(0,J29-Parameters!$B$13),IF(AND($B30="Work",$C30=7),MAX(0,J29-Parameters!$B$14),IF(AND($B30="Gather",$C30=7),MIN(Parameters!$B$10,J29+Parameters!$B$16),J29)))) -> 25 | K30: =IF($K29<=0,0,MAX(0,K29-L30*Parameters!$B$6-IF($B30="Gather",Parameters!$B$17,0))) -> 45 | L30: =IF($K29<=0,0,MAX(0,IF($B30="Travel",Parameters!$B$13*7,IF($B30="Work",Parameters!$B$14,0))-(SUM(D29:J29)-SUM(D30:J30)))) -> 0 | M30: =IF(K30<=0,"RUN OVER","alive") -> alive
A31: 25 | B31: Travel | D31: =IF($K30<=0,D30,IF($B31="Travel",MAX(0,D30-Parameters!$B$13),IF(AND($B31="Work",$C31=1),MAX(0,D30-Parameters!$B$14),IF(AND($B31="Gather",$C31=1),MIN(Parameters!$B$10,D30+Parameters!$B$16),D30)))) -> 0 | E31: =IF($K30<=0,E30,IF($B31="Travel",MAX(0,E30-Parameters!$B$13),IF(AND($B31="Work",$C31=2),MAX(0,E30-Parameters!$B$14),IF(AND($B31="Gather",$C31=2),MIN(Parameters!$B$10,E30+Parameters!$B$16),E30)))) -> 55 | F31: =IF($K30<=0,F30,IF($B31="Travel",MAX(0,F30-Parameters!$B$13),IF(AND($B31="Work",$C31=3),MAX(0,F30-Parameters!$B$14),IF(AND($B31="Gather",$C31=3),MIN(Parameters!$B$10,F30+Parameters!$B$16),F30)))) -> 55 | G31: =IF($K30<=0,G30,IF($B31="Travel",MAX(0,G30-Parameters!$B$13),IF(AND($B31="Work",$C31=4),MAX(0,G30-Parameters!$B$14),IF(AND($B31="Gather",$C31=4),MIN(Parameters!$B$10,G30+Parameters!$B$16),G30)))) -> 55 | H31: =IF($K30<=0,H30,IF($B31="Travel",MAX(0,H30-Parameters!$B$13),IF(AND($B31="Work",$C31=5),MAX(0,H30-Parameters!$B$14),IF(AND($B31="Gather",$C31=5),MIN(Parameters!$B$10,H30+Parameters!$B$16),H30)))) -> 55 | I31: =IF($K30<=0,I30,IF($B31="Travel",MAX(0,I30-Parameters!$B$13),IF(AND($B31="Work",$C31=6),MAX(0,I30-Parameters!$B$14),IF(AND($B31="Gather",$C31=6),MIN(Parameters!$B$10,I30+Parameters!$B$16),I30)))) -> 55 | J31: =IF($K30<=0,J30,IF($B31="Travel",MAX(0,J30-Parameters!$B$13),IF(AND($B31="Work",$C31=7),MAX(0,J30-Parameters!$B$14),IF(AND($B31="Gather",$C31=7),MIN(Parameters!$B$10,J30+Parameters!$B$16),J30)))) -> 10 | K31: =IF($K30<=0,0,MAX(0,K30-L31*Parameters!$B$6-IF($B31="Gather",Parameters!$B$17,0))) -> 36 | L31: =IF($K30<=0,0,MAX(0,IF($B31="Travel",Parameters!$B$13*7,IF($B31="Work",Parameters!$B$14,0))-(SUM(D30:J30)-SUM(D31:J31)))) -> 9 | M31: =IF(K31<=0,"RUN OVER","alive") -> alive
A32: 26 | B32: Work | C32: 2 | D32: =IF($K31<=0,D31,IF($B32="Travel",MAX(0,D31-Parameters!$B$13),IF(AND($B32="Work",$C32=1),MAX(0,D31-Parameters!$B$14),IF(AND($B32="Gather",$C32=1),MIN(Parameters!$B$10,D31+Parameters!$B$16),D31)))) -> 0 | E32: =IF($K31<=0,E31,IF($B32="Travel",MAX(0,E31-Parameters!$B$13),IF(AND($B32="Work",$C32=2),MAX(0,E31-Parameters!$B$14),IF(AND($B32="Gather",$C32=2),MIN(Parameters!$B$10,E31+Parameters!$B$16),E31)))) -> 47 | F32: =IF($K31<=0,F31,IF($B32="Travel",MAX(0,F31-Parameters!$B$13),IF(AND($B32="Work",$C32=3),MAX(0,F31-Parameters!$B$14),IF(AND($B32="Gather",$C32=3),MIN(Parameters!$B$10,F31+Parameters!$B$16),F31)))) -> 55 | G32: =IF($K31<=0,G31,IF($B32="Travel",MAX(0,G31-Parameters!$B$13),IF(AND($B32="Work",$C32=4),MAX(0,G31-Parameters!$B$14),IF(AND($B32="Gather",$C32=4),MIN(Parameters!$B$10,G31+Parameters!$B$16),G31)))) -> 55 | H32: =IF($K31<=0,H31,IF($B32="Travel",MAX(0,H31-Parameters!$B$13),IF(AND($B32="Work",$C32=5),MAX(0,H31-Parameters!$B$14),IF(AND($B32="Gather",$C32=5),MIN(Parameters!$B$10,H31+Parameters!$B$16),H31)))) -> 55 | I32: =IF($K31<=0,I31,IF($B32="Travel",MAX(0,I31-Parameters!$B$13),IF(AND($B32="Work",$C32=6),MAX(0,I31-Parameters!$B$14),IF(AND($B32="Gather",$C32=6),MIN(Parameters!$B$10,I31+Parameters!$B$16),I31)))) -> 55 | J32: =IF($K31<=0,J31,IF($B32="Travel",MAX(0,J31-Parameters!$B$13),IF(AND($B32="Work",$C32=7),MAX(0,J31-Parameters!$B$14),IF(AND($B32="Gather",$C32=7),MIN(Parameters!$B$10,J31+Parameters!$B$16),J31)))) -> 10 | K32: =IF($K31<=0,0,MAX(0,K31-L32*Parameters!$B$6-IF($B32="Gather",Parameters!$B$17,0))) -> 36 | L32: =IF($K31<=0,0,MAX(0,IF($B32="Travel",Parameters!$B$13*7,IF($B32="Work",Parameters!$B$14,0))-(SUM(D31:J31)-SUM(D32:J32)))) -> 0 | M32: =IF(K32<=0,"RUN OVER","alive") -> alive
A33: 27 | B33: Work | C33: 2 | D33: =IF($K32<=0,D32,IF($B33="Travel",MAX(0,D32-Parameters!$B$13),IF(AND($B33="Work",$C33=1),MAX(0,D32-Parameters!$B$14),IF(AND($B33="Gather",$C33=1),MIN(Parameters!$B$10,D32+Parameters!$B$16),D32)))) -> 0 | E33: =IF($K32<=0,E32,IF($B33="Travel",MAX(0,E32-Parameters!$B$13),IF(AND($B33="Work",$C33=2),MAX(0,E32-Parameters!$B$14),IF(AND($B33="Gather",$C33=2),MIN(Parameters!$B$10,E32+Parameters!$B$16),E32)))) -> 39 | F33: =IF($K32<=0,F32,IF($B33="Travel",MAX(0,F32-Parameters!$B$13),IF(AND($B33="Work",$C33=3),MAX(0,F32-Parameters!$B$14),IF(AND($B33="Gather",$C33=3),MIN(Parameters!$B$10,F32+Parameters!$B$16),F32)))) -> 55 | G33: =IF($K32<=0,G32,IF($B33="Travel",MAX(0,G32-Parameters!$B$13),IF(AND($B33="Work",$C33=4),MAX(0,G32-Parameters!$B$14),IF(AND($B33="Gather",$C33=4),MIN(Parameters!$B$10,G32+Parameters!$B$16),G32)))) -> 55 | H33: =IF($K32<=0,H32,IF($B33="Travel",MAX(0,H32-Parameters!$B$13),IF(AND($B33="Work",$C33=5),MAX(0,H32-Parameters!$B$14),IF(AND($B33="Gather",$C33=5),MIN(Parameters!$B$10,H32+Parameters!$B$16),H32)))) -> 55 | I33: =IF($K32<=0,I32,IF($B33="Travel",MAX(0,I32-Parameters!$B$13),IF(AND($B33="Work",$C33=6),MAX(0,I32-Parameters!$B$14),IF(AND($B33="Gather",$C33=6),MIN(Parameters!$B$10,I32+Parameters!$B$16),I32)))) -> 55 | J33: =IF($K32<=0,J32,IF($B33="Travel",MAX(0,J32-Parameters!$B$13),IF(AND($B33="Work",$C33=7),MAX(0,J32-Parameters!$B$14),IF(AND($B33="Gather",$C33=7),MIN(Parameters!$B$10,J32+Parameters!$B$16),J32)))) -> 10 | K33: =IF($K32<=0,0,MAX(0,K32-L33*Parameters!$B$6-IF($B33="Gather",Parameters!$B$17,0))) -> 36 | L33: =IF($K32<=0,0,MAX(0,IF($B33="Travel",Parameters!$B$13*7,IF($B33="Work",Parameters!$B$14,0))-(SUM(D32:J32)-SUM(D33:J33)))) -> 0 | M33: =IF(K33<=0,"RUN OVER","alive") -> alive
A34: 28 | B34: Work | C34: 2 | D34: =IF($K33<=0,D33,IF($B34="Travel",MAX(0,D33-Parameters!$B$13),IF(AND($B34="Work",$C34=1),MAX(0,D33-Parameters!$B$14),IF(AND($B34="Gather",$C34=1),MIN(Parameters!$B$10,D33+Parameters!$B$16),D33)))) -> 0 | E34: =IF($K33<=0,E33,IF($B34="Travel",MAX(0,E33-Parameters!$B$13),IF(AND($B34="Work",$C34=2),MAX(0,E33-Parameters!$B$14),IF(AND($B34="Gather",$C34=2),MIN(Parameters!$B$10,E33+Parameters!$B$16),E33)))) -> 31 | F34: =IF($K33<=0,F33,IF($B34="Travel",MAX(0,F33-Parameters!$B$13),IF(AND($B34="Work",$C34=3),MAX(0,F33-Parameters!$B$14),IF(AND($B34="Gather",$C34=3),MIN(Parameters!$B$10,F33+Parameters!$B$16),F33)))) -> 55 | G34: =IF($K33<=0,G33,IF($B34="Travel",MAX(0,G33-Parameters!$B$13),IF(AND($B34="Work",$C34=4),MAX(0,G33-Parameters!$B$14),IF(AND($B34="Gather",$C34=4),MIN(Parameters!$B$10,G33+Parameters!$B$16),G33)))) -> 55 | H34: =IF($K33<=0,H33,IF($B34="Travel",MAX(0,H33-Parameters!$B$13),IF(AND($B34="Work",$C34=5),MAX(0,H33-Parameters!$B$14),IF(AND($B34="Gather",$C34=5),MIN(Parameters!$B$10,H33+Parameters!$B$16),H33)))) -> 55 | I34: =IF($K33<=0,I33,IF($B34="Travel",MAX(0,I33-Parameters!$B$13),IF(AND($B34="Work",$C34=6),MAX(0,I33-Parameters!$B$14),IF(AND($B34="Gather",$C34=6),MIN(Parameters!$B$10,I33+Parameters!$B$16),I33)))) -> 55 | J34: =IF($K33<=0,J33,IF($B34="Travel",MAX(0,J33-Parameters!$B$13),IF(AND($B34="Work",$C34=7),MAX(0,J33-Parameters!$B$14),IF(AND($B34="Gather",$C34=7),MIN(Parameters!$B$10,J33+Parameters!$B$16),J33)))) -> 10 | K34: =IF($K33<=0,0,MAX(0,K33-L34*Parameters!$B$6-IF($B34="Gather",Parameters!$B$17,0))) -> 36 | L34: =IF($K33<=0,0,MAX(0,IF($B34="Travel",Parameters!$B$13*7,IF($B34="Work",Parameters!$B$14,0))-(SUM(D33:J33)-SUM(D34:J34)))) -> 0 | M34: =IF(K34<=0,"RUN OVER","alive") -> alive
A35: 29 | B35: Work | C35: 2 | D35: =IF($K34<=0,D34,IF($B35="Travel",MAX(0,D34-Parameters!$B$13),IF(AND($B35="Work",$C35=1),MAX(0,D34-Parameters!$B$14),IF(AND($B35="Gather",$C35=1),MIN(Parameters!$B$10,D34+Parameters!$B$16),D34)))) -> 0 | E35: =IF($K34<=0,E34,IF($B35="Travel",MAX(0,E34-Parameters!$B$13),IF(AND($B35="Work",$C35=2),MAX(0,E34-Parameters!$B$14),IF(AND($B35="Gather",$C35=2),MIN(Parameters!$B$10,E34+Parameters!$B$16),E34)))) -> 23 | F35: =IF($K34<=0,F34,IF($B35="Travel",MAX(0,F34-Parameters!$B$13),IF(AND($B35="Work",$C35=3),MAX(0,F34-Parameters!$B$14),IF(AND($B35="Gather",$C35=3),MIN(Parameters!$B$10,F34+Parameters!$B$16),F34)))) -> 55 | G35: =IF($K34<=0,G34,IF($B35="Travel",MAX(0,G34-Parameters!$B$13),IF(AND($B35="Work",$C35=4),MAX(0,G34-Parameters!$B$14),IF(AND($B35="Gather",$C35=4),MIN(Parameters!$B$10,G34+Parameters!$B$16),G34)))) -> 55 | H35: =IF($K34<=0,H34,IF($B35="Travel",MAX(0,H34-Parameters!$B$13),IF(AND($B35="Work",$C35=5),MAX(0,H34-Parameters!$B$14),IF(AND($B35="Gather",$C35=5),MIN(Parameters!$B$10,H34+Parameters!$B$16),H34)))) -> 55 | I35: =IF($K34<=0,I34,IF($B35="Travel",MAX(0,I34-Parameters!$B$13),IF(AND($B35="Work",$C35=6),MAX(0,I34-Parameters!$B$14),IF(AND($B35="Gather",$C35=6),MIN(Parameters!$B$10,I34+Parameters!$B$16),I34)))) -> 55 | J35: =IF($K34<=0,J34,IF($B35="Travel",MAX(0,J34-Parameters!$B$13),IF(AND($B35="Work",$C35=7),MAX(0,J34-Parameters!$B$14),IF(AND($B35="Gather",$C35=7),MIN(Parameters!$B$10,J34+Parameters!$B$16),J34)))) -> 10 | K35: =IF($K34<=0,0,MAX(0,K34-L35*Parameters!$B$6-IF($B35="Gather",Parameters!$B$17,0))) -> 36 | L35: =IF($K34<=0,0,MAX(0,IF($B35="Travel",Parameters!$B$13*7,IF($B35="Work",Parameters!$B$14,0))-(SUM(D34:J34)-SUM(D35:J35)))) -> 0 | M35: =IF(K35<=0,"RUN OVER","alive") -> alive
A36: 30 | B36: Work | C36: 2 | D36: =IF($K35<=0,D35,IF($B36="Travel",MAX(0,D35-Parameters!$B$13),IF(AND($B36="Work",$C36=1),MAX(0,D35-Parameters!$B$14),IF(AND($B36="Gather",$C36=1),MIN(Parameters!$B$10,D35+Parameters!$B$16),D35)))) -> 0 | E36: =IF($K35<=0,E35,IF($B36="Travel",MAX(0,E35-Parameters!$B$13),IF(AND($B36="Work",$C36=2),MAX(0,E35-Parameters!$B$14),IF(AND($B36="Gather",$C36=2),MIN(Parameters!$B$10,E35+Parameters!$B$16),E35)))) -> 15 | F36: =IF($K35<=0,F35,IF($B36="Travel",MAX(0,F35-Parameters!$B$13),IF(AND($B36="Work",$C36=3),MAX(0,F35-Parameters!$B$14),IF(AND($B36="Gather",$C36=3),MIN(Parameters!$B$10,F35+Parameters!$B$16),F35)))) -> 55 | G36: =IF($K35<=0,G35,IF($B36="Travel",MAX(0,G35-Parameters!$B$13),IF(AND($B36="Work",$C36=4),MAX(0,G35-Parameters!$B$14),IF(AND($B36="Gather",$C36=4),MIN(Parameters!$B$10,G35+Parameters!$B$16),G35)))) -> 55 | H36: =IF($K35<=0,H35,IF($B36="Travel",MAX(0,H35-Parameters!$B$13),IF(AND($B36="Work",$C36=5),MAX(0,H35-Parameters!$B$14),IF(AND($B36="Gather",$C36=5),MIN(Parameters!$B$10,H35+Parameters!$B$16),H35)))) -> 55 | I36: =IF($K35<=0,I35,IF($B36="Travel",MAX(0,I35-Parameters!$B$13),IF(AND($B36="Work",$C36=6),MAX(0,I35-Parameters!$B$14),IF(AND($B36="Gather",$C36=6),MIN(Parameters!$B$10,I35+Parameters!$B$16),I35)))) -> 55 | J36: =IF($K35<=0,J35,IF($B36="Travel",MAX(0,J35-Parameters!$B$13),IF(AND($B36="Work",$C36=7),MAX(0,J35-Parameters!$B$14),IF(AND($B36="Gather",$C36=7),MIN(Parameters!$B$10,J35+Parameters!$B$16),J35)))) -> 10 | K36: =IF($K35<=0,0,MAX(0,K35-L36*Parameters!$B$6-IF($B36="Gather",Parameters!$B$17,0))) -> 36 | L36: =IF($K35<=0,0,MAX(0,IF($B36="Travel",Parameters!$B$13*7,IF($B36="Work",Parameters!$B$14,0))-(SUM(D35:J35)-SUM(D36:J36)))) -> 0 | M36: =IF(K36<=0,"RUN OVER","alive") -> alive
A37: 31 | B37: Work | C37: 2 | D37: =IF($K36<=0,D36,IF($B37="Travel",MAX(0,D36-Parameters!$B$13),IF(AND($B37="Work",$C37=1),MAX(0,D36-Parameters!$B$14),IF(AND($B37="Gather",$C37=1),MIN(Parameters!$B$10,D36+Parameters!$B$16),D36)))) -> 0 | E37: =IF($K36<=0,E36,IF($B37="Travel",MAX(0,E36-Parameters!$B$13),IF(AND($B37="Work",$C37=2),MAX(0,E36-Parameters!$B$14),IF(AND($B37="Gather",$C37=2),MIN(Parameters!$B$10,E36+Parameters!$B$16),E36)))) -> 7 | F37: =IF($K36<=0,F36,IF($B37="Travel",MAX(0,F36-Parameters!$B$13),IF(AND($B37="Work",$C37=3),MAX(0,F36-Parameters!$B$14),IF(AND($B37="Gather",$C37=3),MIN(Parameters!$B$10,F36+Parameters!$B$16),F36)))) -> 55 | G37: =IF($K36<=0,G36,IF($B37="Travel",MAX(0,G36-Parameters!$B$13),IF(AND($B37="Work",$C37=4),MAX(0,G36-Parameters!$B$14),IF(AND($B37="Gather",$C37=4),MIN(Parameters!$B$10,G36+Parameters!$B$16),G36)))) -> 55 | H37: =IF($K36<=0,H36,IF($B37="Travel",MAX(0,H36-Parameters!$B$13),IF(AND($B37="Work",$C37=5),MAX(0,H36-Parameters!$B$14),IF(AND($B37="Gather",$C37=5),MIN(Parameters!$B$10,H36+Parameters!$B$16),H36)))) -> 55 | I37: =IF($K36<=0,I36,IF($B37="Travel",MAX(0,I36-Parameters!$B$13),IF(AND($B37="Work",$C37=6),MAX(0,I36-Parameters!$B$14),IF(AND($B37="Gather",$C37=6),MIN(Parameters!$B$10,I36+Parameters!$B$16),I36)))) -> 55 | J37: =IF($K36<=0,J36,IF($B37="Travel",MAX(0,J36-Parameters!$B$13),IF(AND($B37="Work",$C37=7),MAX(0,J36-Parameters!$B$14),IF(AND($B37="Gather",$C37=7),MIN(Parameters!$B$10,J36+Parameters!$B$16),J36)))) -> 10 | K37: =IF($K36<=0,0,MAX(0,K36-L37*Parameters!$B$6-IF($B37="Gather",Parameters!$B$17,0))) -> 36 | L37: =IF($K36<=0,0,MAX(0,IF($B37="Travel",Parameters!$B$13*7,IF($B37="Work",Parameters!$B$14,0))-(SUM(D36:J36)-SUM(D37:J37)))) -> 0 | M37: =IF(K37<=0,"RUN OVER","alive") -> alive
A38: 32 | B38: Work | C38: 2 | D38: =IF($K37<=0,D37,IF($B38="Travel",MAX(0,D37-Parameters!$B$13),IF(AND($B38="Work",$C38=1),MAX(0,D37-Parameters!$B$14),IF(AND($B38="Gather",$C38=1),MIN(Parameters!$B$10,D37+Parameters!$B$16),D37)))) -> 0 | E38: =IF($K37<=0,E37,IF($B38="Travel",MAX(0,E37-Parameters!$B$13),IF(AND($B38="Work",$C38=2),MAX(0,E37-Parameters!$B$14),IF(AND($B38="Gather",$C38=2),MIN(Parameters!$B$10,E37+Parameters!$B$16),E37)))) -> 0 | F38: =IF($K37<=0,F37,IF($B38="Travel",MAX(0,F37-Parameters!$B$13),IF(AND($B38="Work",$C38=3),MAX(0,F37-Parameters!$B$14),IF(AND($B38="Gather",$C38=3),MIN(Parameters!$B$10,F37+Parameters!$B$16),F37)))) -> 55 | G38: =IF($K37<=0,G37,IF($B38="Travel",MAX(0,G37-Parameters!$B$13),IF(AND($B38="Work",$C38=4),MAX(0,G37-Parameters!$B$14),IF(AND($B38="Gather",$C38=4),MIN(Parameters!$B$10,G37+Parameters!$B$16),G37)))) -> 55 | H38: =IF($K37<=0,H37,IF($B38="Travel",MAX(0,H37-Parameters!$B$13),IF(AND($B38="Work",$C38=5),MAX(0,H37-Parameters!$B$14),IF(AND($B38="Gather",$C38=5),MIN(Parameters!$B$10,H37+Parameters!$B$16),H37)))) -> 55 | I38: =IF($K37<=0,I37,IF($B38="Travel",MAX(0,I37-Parameters!$B$13),IF(AND($B38="Work",$C38=6),MAX(0,I37-Parameters!$B$14),IF(AND($B38="Gather",$C38=6),MIN(Parameters!$B$10,I37+Parameters!$B$16),I37)))) -> 55 | J38: =IF($K37<=0,J37,IF($B38="Travel",MAX(0,J37-Parameters!$B$13),IF(AND($B38="Work",$C38=7),MAX(0,J37-Parameters!$B$14),IF(AND($B38="Gather",$C38=7),MIN(Parameters!$B$10,J37+Parameters!$B$16),J37)))) -> 10 | K38: =IF($K37<=0,0,MAX(0,K37-L38*Parameters!$B$6-IF($B38="Gather",Parameters!$B$17,0))) -> 35 | L38: =IF($K37<=0,0,MAX(0,IF($B38="Travel",Parameters!$B$13*7,IF($B38="Work",Parameters!$B$14,0))-(SUM(D37:J37)-SUM(D38:J38)))) -> 1 | M38: =IF(K38<=0,"RUN OVER","alive") -> alive
A39: 33 | B39: Work | C39: 2 | D39: =IF($K38<=0,D38,IF($B39="Travel",MAX(0,D38-Parameters!$B$13),IF(AND($B39="Work",$C39=1),MAX(0,D38-Parameters!$B$14),IF(AND($B39="Gather",$C39=1),MIN(Parameters!$B$10,D38+Parameters!$B$16),D38)))) -> 0 | E39: =IF($K38<=0,E38,IF($B39="Travel",MAX(0,E38-Parameters!$B$13),IF(AND($B39="Work",$C39=2),MAX(0,E38-Parameters!$B$14),IF(AND($B39="Gather",$C39=2),MIN(Parameters!$B$10,E38+Parameters!$B$16),E38)))) -> 0 | F39: =IF($K38<=0,F38,IF($B39="Travel",MAX(0,F38-Parameters!$B$13),IF(AND($B39="Work",$C39=3),MAX(0,F38-Parameters!$B$14),IF(AND($B39="Gather",$C39=3),MIN(Parameters!$B$10,F38+Parameters!$B$16),F38)))) -> 55 | G39: =IF($K38<=0,G38,IF($B39="Travel",MAX(0,G38-Parameters!$B$13),IF(AND($B39="Work",$C39=4),MAX(0,G38-Parameters!$B$14),IF(AND($B39="Gather",$C39=4),MIN(Parameters!$B$10,G38+Parameters!$B$16),G38)))) -> 55 | H39: =IF($K38<=0,H38,IF($B39="Travel",MAX(0,H38-Parameters!$B$13),IF(AND($B39="Work",$C39=5),MAX(0,H38-Parameters!$B$14),IF(AND($B39="Gather",$C39=5),MIN(Parameters!$B$10,H38+Parameters!$B$16),H38)))) -> 55 | I39: =IF($K38<=0,I38,IF($B39="Travel",MAX(0,I38-Parameters!$B$13),IF(AND($B39="Work",$C39=6),MAX(0,I38-Parameters!$B$14),IF(AND($B39="Gather",$C39=6),MIN(Parameters!$B$10,I38+Parameters!$B$16),I38)))) -> 55 | J39: =IF($K38<=0,J38,IF($B39="Travel",MAX(0,J38-Parameters!$B$13),IF(AND($B39="Work",$C39=7),MAX(0,J38-Parameters!$B$14),IF(AND($B39="Gather",$C39=7),MIN(Parameters!$B$10,J38+Parameters!$B$16),J38)))) -> 10 | K39: =IF($K38<=0,0,MAX(0,K38-L39*Parameters!$B$6-IF($B39="Gather",Parameters!$B$17,0))) -> 27 | L39: =IF($K38<=0,0,MAX(0,IF($B39="Travel",Parameters!$B$13*7,IF($B39="Work",Parameters!$B$14,0))-(SUM(D38:J38)-SUM(D39:J39)))) -> 8 | M39: =IF(K39<=0,"RUN OVER","alive") -> alive
A40: 34 | B40: Travel | D40: =IF($K39<=0,D39,IF($B40="Travel",MAX(0,D39-Parameters!$B$13),IF(AND($B40="Work",$C40=1),MAX(0,D39-Parameters!$B$14),IF(AND($B40="Gather",$C40=1),MIN(Parameters!$B$10,D39+Parameters!$B$16),D39)))) -> 0 | E40: =IF($K39<=0,E39,IF($B40="Travel",MAX(0,E39-Parameters!$B$13),IF(AND($B40="Work",$C40=2),MAX(0,E39-Parameters!$B$14),IF(AND($B40="Gather",$C40=2),MIN(Parameters!$B$10,E39+Parameters!$B$16),E39)))) -> 0 | F40: =IF($K39<=0,F39,IF($B40="Travel",MAX(0,F39-Parameters!$B$13),IF(AND($B40="Work",$C40=3),MAX(0,F39-Parameters!$B$14),IF(AND($B40="Gather",$C40=3),MIN(Parameters!$B$10,F39+Parameters!$B$16),F39)))) -> 40 | G40: =IF($K39<=0,G39,IF($B40="Travel",MAX(0,G39-Parameters!$B$13),IF(AND($B40="Work",$C40=4),MAX(0,G39-Parameters!$B$14),IF(AND($B40="Gather",$C40=4),MIN(Parameters!$B$10,G39+Parameters!$B$16),G39)))) -> 40 | H40: =IF($K39<=0,H39,IF($B40="Travel",MAX(0,H39-Parameters!$B$13),IF(AND($B40="Work",$C40=5),MAX(0,H39-Parameters!$B$14),IF(AND($B40="Gather",$C40=5),MIN(Parameters!$B$10,H39+Parameters!$B$16),H39)))) -> 40 | I40: =IF($K39<=0,I39,IF($B40="Travel",MAX(0,I39-Parameters!$B$13),IF(AND($B40="Work",$C40=6),MAX(0,I39-Parameters!$B$14),IF(AND($B40="Gather",$C40=6),MIN(Parameters!$B$10,I39+Parameters!$B$16),I39)))) -> 40 | J40: =IF($K39<=0,J39,IF($B40="Travel",MAX(0,J39-Parameters!$B$13),IF(AND($B40="Work",$C40=7),MAX(0,J39-Parameters!$B$14),IF(AND($B40="Gather",$C40=7),MIN(Parameters!$B$10,J39+Parameters!$B$16),J39)))) -> 0 | K40: =IF($K39<=0,0,MAX(0,K39-L40*Parameters!$B$6-IF($B40="Gather",Parameters!$B$17,0))) -> 0 | L40: =IF($K39<=0,0,MAX(0,IF($B40="Travel",Parameters!$B$13*7,IF($B40="Work",Parameters!$B$14,0))-(SUM(D39:J39)-SUM(D40:J40)))) -> 35 | M40: =IF(K40<=0,"RUN OVER","alive") -> RUN OVER
A41: 35 | B41: Work | C41: 3 | D41: =IF($K40<=0,D40,IF($B41="Travel",MAX(0,D40-Parameters!$B$13),IF(AND($B41="Work",$C41=1),MAX(0,D40-Parameters!$B$14),IF(AND($B41="Gather",$C41=1),MIN(Parameters!$B$10,D40+Parameters!$B$16),D40)))) -> 0 | E41: =IF($K40<=0,E40,IF($B41="Travel",MAX(0,E40-Parameters!$B$13),IF(AND($B41="Work",$C41=2),MAX(0,E40-Parameters!$B$14),IF(AND($B41="Gather",$C41=2),MIN(Parameters!$B$10,E40+Parameters!$B$16),E40)))) -> 0 | F41: =IF($K40<=0,F40,IF($B41="Travel",MAX(0,F40-Parameters!$B$13),IF(AND($B41="Work",$C41=3),MAX(0,F40-Parameters!$B$14),IF(AND($B41="Gather",$C41=3),MIN(Parameters!$B$10,F40+Parameters!$B$16),F40)))) -> 40 | G41: =IF($K40<=0,G40,IF($B41="Travel",MAX(0,G40-Parameters!$B$13),IF(AND($B41="Work",$C41=4),MAX(0,G40-Parameters!$B$14),IF(AND($B41="Gather",$C41=4),MIN(Parameters!$B$10,G40+Parameters!$B$16),G40)))) -> 40 | H41: =IF($K40<=0,H40,IF($B41="Travel",MAX(0,H40-Parameters!$B$13),IF(AND($B41="Work",$C41=5),MAX(0,H40-Parameters!$B$14),IF(AND($B41="Gather",$C41=5),MIN(Parameters!$B$10,H40+Parameters!$B$16),H40)))) -> 40 | I41: =IF($K40<=0,I40,IF($B41="Travel",MAX(0,I40-Parameters!$B$13),IF(AND($B41="Work",$C41=6),MAX(0,I40-Parameters!$B$14),IF(AND($B41="Gather",$C41=6),MIN(Parameters!$B$10,I40+Parameters!$B$16),I40)))) -> 40 | J41: =IF($K40<=0,J40,IF($B41="Travel",MAX(0,J40-Parameters!$B$13),IF(AND($B41="Work",$C41=7),MAX(0,J40-Parameters!$B$14),IF(AND($B41="Gather",$C41=7),MIN(Parameters!$B$10,J40+Parameters!$B$16),J40)))) -> 0 | K41: =IF($K40<=0,0,MAX(0,K40-L41*Parameters!$B$6-IF($B41="Gather",Parameters!$B$17,0))) -> 0 | L41: =IF($K40<=0,0,MAX(0,IF($B41="Travel",Parameters!$B$13*7,IF($B41="Work",Parameters!$B$14,0))-(SUM(D40:J40)-SUM(D41:J41)))) -> 0 | M41: =IF(K41<=0,"RUN OVER","alive") -> RUN OVER
A42: 36 | B42: Work | C42: 3 | D42: =IF($K41<=0,D41,IF($B42="Travel",MAX(0,D41-Parameters!$B$13),IF(AND($B42="Work",$C42=1),MAX(0,D41-Parameters!$B$14),IF(AND($B42="Gather",$C42=1),MIN(Parameters!$B$10,D41+Parameters!$B$16),D41)))) -> 0 | E42: =IF($K41<=0,E41,IF($B42="Travel",MAX(0,E41-Parameters!$B$13),IF(AND($B42="Work",$C42=2),MAX(0,E41-Parameters!$B$14),IF(AND($B42="Gather",$C42=2),MIN(Parameters!$B$10,E41+Parameters!$B$16),E41)))) -> 0 | F42: =IF($K41<=0,F41,IF($B42="Travel",MAX(0,F41-Parameters!$B$13),IF(AND($B42="Work",$C42=3),MAX(0,F41-Parameters!$B$14),IF(AND($B42="Gather",$C42=3),MIN(Parameters!$B$10,F41+Parameters!$B$16),F41)))) -> 40 | G42: =IF($K41<=0,G41,IF($B42="Travel",MAX(0,G41-Parameters!$B$13),IF(AND($B42="Work",$C42=4),MAX(0,G41-Parameters!$B$14),IF(AND($B42="Gather",$C42=4),MIN(Parameters!$B$10,G41+Parameters!$B$16),G41)))) -> 40 | H42: =IF($K41<=0,H41,IF($B42="Travel",MAX(0,H41-Parameters!$B$13),IF(AND($B42="Work",$C42=5),MAX(0,H41-Parameters!$B$14),IF(AND($B42="Gather",$C42=5),MIN(Parameters!$B$10,H41+Parameters!$B$16),H41)))) -> 40 | I42: =IF($K41<=0,I41,IF($B42="Travel",MAX(0,I41-Parameters!$B$13),IF(AND($B42="Work",$C42=6),MAX(0,I41-Parameters!$B$14),IF(AND($B42="Gather",$C42=6),MIN(Parameters!$B$10,I41+Parameters!$B$16),I41)))) -> 40 | J42: =IF($K41<=0,J41,IF($B42="Travel",MAX(0,J41-Parameters!$B$13),IF(AND($B42="Work",$C42=7),MAX(0,J41-Parameters!$B$14),IF(AND($B42="Gather",$C42=7),MIN(Parameters!$B$10,J41+Parameters!$B$16),J41)))) -> 0 | K42: =IF($K41<=0,0,MAX(0,K41-L42*Parameters!$B$6-IF($B42="Gather",Parameters!$B$17,0))) -> 0 | L42: =IF($K41<=0,0,MAX(0,IF($B42="Travel",Parameters!$B$13*7,IF($B42="Work",Parameters!$B$14,0))-(SUM(D41:J41)-SUM(D42:J42)))) -> 0 | M42: =IF(K42<=0,"RUN OVER","alive") -> RUN OVER
A43: 37 | B43: Work | C43: 3 | D43: =IF($K42<=0,D42,IF($B43="Travel",MAX(0,D42-Parameters!$B$13),IF(AND($B43="Work",$C43=1),MAX(0,D42-Parameters!$B$14),IF(AND($B43="Gather",$C43=1),MIN(Parameters!$B$10,D42+Parameters!$B$16),D42)))) -> 0 | E43: =IF($K42<=0,E42,IF($B43="Travel",MAX(0,E42-Parameters!$B$13),IF(AND($B43="Work",$C43=2),MAX(0,E42-Parameters!$B$14),IF(AND($B43="Gather",$C43=2),MIN(Parameters!$B$10,E42+Parameters!$B$16),E42)))) -> 0 | F43: =IF($K42<=0,F42,IF($B43="Travel",MAX(0,F42-Parameters!$B$13),IF(AND($B43="Work",$C43=3),MAX(0,F42-Parameters!$B$14),IF(AND($B43="Gather",$C43=3),MIN(Parameters!$B$10,F42+Parameters!$B$16),F42)))) -> 40 | G43: =IF($K42<=0,G42,IF($B43="Travel",MAX(0,G42-Parameters!$B$13),IF(AND($B43="Work",$C43=4),MAX(0,G42-Parameters!$B$14),IF(AND($B43="Gather",$C43=4),MIN(Parameters!$B$10,G42+Parameters!$B$16),G42)))) -> 40 | H43: =IF($K42<=0,H42,IF($B43="Travel",MAX(0,H42-Parameters!$B$13),IF(AND($B43="Work",$C43=5),MAX(0,H42-Parameters!$B$14),IF(AND($B43="Gather",$C43=5),MIN(Parameters!$B$10,H42+Parameters!$B$16),H42)))) -> 40 | I43: =IF($K42<=0,I42,IF($B43="Travel",MAX(0,I42-Parameters!$B$13),IF(AND($B43="Work",$C43=6),MAX(0,I42-Parameters!$B$14),IF(AND($B43="Gather",$C43=6),MIN(Parameters!$B$10,I42+Parameters!$B$16),I42)))) -> 40 | J43: =IF($K42<=0,J42,IF($B43="Travel",MAX(0,J42-Parameters!$B$13),IF(AND($B43="Work",$C43=7),MAX(0,J42-Parameters!$B$14),IF(AND($B43="Gather",$C43=7),MIN(Parameters!$B$10,J42+Parameters!$B$16),J42)))) -> 0 | K43: =IF($K42<=0,0,MAX(0,K42-L43*Parameters!$B$6-IF($B43="Gather",Parameters!$B$17,0))) -> 0 | L43: =IF($K42<=0,0,MAX(0,IF($B43="Travel",Parameters!$B$13*7,IF($B43="Work",Parameters!$B$14,0))-(SUM(D42:J42)-SUM(D43:J43)))) -> 0 | M43: =IF(K43<=0,"RUN OVER","alive") -> RUN OVER
A44: 38 | B44: Work | C44: 3 | D44: =IF($K43<=0,D43,IF($B44="Travel",MAX(0,D43-Parameters!$B$13),IF(AND($B44="Work",$C44=1),MAX(0,D43-Parameters!$B$14),IF(AND($B44="Gather",$C44=1),MIN(Parameters!$B$10,D43+Parameters!$B$16),D43)))) -> 0 | E44: =IF($K43<=0,E43,IF($B44="Travel",MAX(0,E43-Parameters!$B$13),IF(AND($B44="Work",$C44=2),MAX(0,E43-Parameters!$B$14),IF(AND($B44="Gather",$C44=2),MIN(Parameters!$B$10,E43+Parameters!$B$16),E43)))) -> 0 | F44: =IF($K43<=0,F43,IF($B44="Travel",MAX(0,F43-Parameters!$B$13),IF(AND($B44="Work",$C44=3),MAX(0,F43-Parameters!$B$14),IF(AND($B44="Gather",$C44=3),MIN(Parameters!$B$10,F43+Parameters!$B$16),F43)))) -> 40 | G44: =IF($K43<=0,G43,IF($B44="Travel",MAX(0,G43-Parameters!$B$13),IF(AND($B44="Work",$C44=4),MAX(0,G43-Parameters!$B$14),IF(AND($B44="Gather",$C44=4),MIN(Parameters!$B$10,G43+Parameters!$B$16),G43)))) -> 40 | H44: =IF($K43<=0,H43,IF($B44="Travel",MAX(0,H43-Parameters!$B$13),IF(AND($B44="Work",$C44=5),MAX(0,H43-Parameters!$B$14),IF(AND($B44="Gather",$C44=5),MIN(Parameters!$B$10,H43+Parameters!$B$16),H43)))) -> 40 | I44: =IF($K43<=0,I43,IF($B44="Travel",MAX(0,I43-Parameters!$B$13),IF(AND($B44="Work",$C44=6),MAX(0,I43-Parameters!$B$14),IF(AND($B44="Gather",$C44=6),MIN(Parameters!$B$10,I43+Parameters!$B$16),I43)))) -> 40 | J44: =IF($K43<=0,J43,IF($B44="Travel",MAX(0,J43-Parameters!$B$13),IF(AND($B44="Work",$C44=7),MAX(0,J43-Parameters!$B$14),IF(AND($B44="Gather",$C44=7),MIN(Parameters!$B$10,J43+Parameters!$B$16),J43)))) -> 0 | K44: =IF($K43<=0,0,MAX(0,K43-L44*Parameters!$B$6-IF($B44="Gather",Parameters!$B$17,0))) -> 0 | L44: =IF($K43<=0,0,MAX(0,IF($B44="Travel",Parameters!$B$13*7,IF($B44="Work",Parameters!$B$14,0))-(SUM(D43:J43)-SUM(D44:J44)))) -> 0 | M44: =IF(K44<=0,"RUN OVER","alive") -> RUN OVER
A45: 39 | B45: Work | C45: 3 | D45: =IF($K44<=0,D44,IF($B45="Travel",MAX(0,D44-Parameters!$B$13),IF(AND($B45="Work",$C45=1),MAX(0,D44-Parameters!$B$14),IF(AND($B45="Gather",$C45=1),MIN(Parameters!$B$10,D44+Parameters!$B$16),D44)))) -> 0 | E45: =IF($K44<=0,E44,IF($B45="Travel",MAX(0,E44-Parameters!$B$13),IF(AND($B45="Work",$C45=2),MAX(0,E44-Parameters!$B$14),IF(AND($B45="Gather",$C45=2),MIN(Parameters!$B$10,E44+Parameters!$B$16),E44)))) -> 0 | F45: =IF($K44<=0,F44,IF($B45="Travel",MAX(0,F44-Parameters!$B$13),IF(AND($B45="Work",$C45=3),MAX(0,F44-Parameters!$B$14),IF(AND($B45="Gather",$C45=3),MIN(Parameters!$B$10,F44+Parameters!$B$16),F44)))) -> 40 | G45: =IF($K44<=0,G44,IF($B45="Travel",MAX(0,G44-Parameters!$B$13),IF(AND($B45="Work",$C45=4),MAX(0,G44-Parameters!$B$14),IF(AND($B45="Gather",$C45=4),MIN(Parameters!$B$10,G44+Parameters!$B$16),G44)))) -> 40 | H45: =IF($K44<=0,H44,IF($B45="Travel",MAX(0,H44-Parameters!$B$13),IF(AND($B45="Work",$C45=5),MAX(0,H44-Parameters!$B$14),IF(AND($B45="Gather",$C45=5),MIN(Parameters!$B$10,H44+Parameters!$B$16),H44)))) -> 40 | I45: =IF($K44<=0,I44,IF($B45="Travel",MAX(0,I44-Parameters!$B$13),IF(AND($B45="Work",$C45=6),MAX(0,I44-Parameters!$B$14),IF(AND($B45="Gather",$C45=6),MIN(Parameters!$B$10,I44+Parameters!$B$16),I44)))) -> 40 | J45: =IF($K44<=0,J44,IF($B45="Travel",MAX(0,J44-Parameters!$B$13),IF(AND($B45="Work",$C45=7),MAX(0,J44-Parameters!$B$14),IF(AND($B45="Gather",$C45=7),MIN(Parameters!$B$10,J44+Parameters!$B$16),J44)))) -> 0 | K45: =IF($K44<=0,0,MAX(0,K44-L45*Parameters!$B$6-IF($B45="Gather",Parameters!$B$17,0))) -> 0 | L45: =IF($K44<=0,0,MAX(0,IF($B45="Travel",Parameters!$B$13*7,IF($B45="Work",Parameters!$B$14,0))-(SUM(D44:J44)-SUM(D45:J45)))) -> 0 | M45: =IF(K45<=0,"RUN OVER","alive") -> RUN OVER
A46: 40 | B46: Work | C46: 3 | D46: =IF($K45<=0,D45,IF($B46="Travel",MAX(0,D45-Parameters!$B$13),IF(AND($B46="Work",$C46=1),MAX(0,D45-Parameters!$B$14),IF(AND($B46="Gather",$C46=1),MIN(Parameters!$B$10,D45+Parameters!$B$16),D45)))) -> 0 | E46: =IF($K45<=0,E45,IF($B46="Travel",MAX(0,E45-Parameters!$B$13),IF(AND($B46="Work",$C46=2),MAX(0,E45-Parameters!$B$14),IF(AND($B46="Gather",$C46=2),MIN(Parameters!$B$10,E45+Parameters!$B$16),E45)))) -> 0 | F46: =IF($K45<=0,F45,IF($B46="Travel",MAX(0,F45-Parameters!$B$13),IF(AND($B46="Work",$C46=3),MAX(0,F45-Parameters!$B$14),IF(AND($B46="Gather",$C46=3),MIN(Parameters!$B$10,F45+Parameters!$B$16),F45)))) -> 40 | G46: =IF($K45<=0,G45,IF($B46="Travel",MAX(0,G45-Parameters!$B$13),IF(AND($B46="Work",$C46=4),MAX(0,G45-Parameters!$B$14),IF(AND($B46="Gather",$C46=4),MIN(Parameters!$B$10,G45+Parameters!$B$16),G45)))) -> 40 | H46: =IF($K45<=0,H45,IF($B46="Travel",MAX(0,H45-Parameters!$B$13),IF(AND($B46="Work",$C46=5),MAX(0,H45-Parameters!$B$14),IF(AND($B46="Gather",$C46=5),MIN(Parameters!$B$10,H45+Parameters!$B$16),H45)))) -> 40 | I46: =IF($K45<=0,I45,IF($B46="Travel",MAX(0,I45-Parameters!$B$13),IF(AND($B46="Work",$C46=6),MAX(0,I45-Parameters!$B$14),IF(AND($B46="Gather",$C46=6),MIN(Parameters!$B$10,I45+Parameters!$B$16),I45)))) -> 40 | J46: =IF($K45<=0,J45,IF($B46="Travel",MAX(0,J45-Parameters!$B$13),IF(AND($B46="Work",$C46=7),MAX(0,J45-Parameters!$B$14),IF(AND($B46="Gather",$C46=7),MIN(Parameters!$B$10,J45+Parameters!$B$16),J45)))) -> 0 | K46: =IF($K45<=0,0,MAX(0,K45-L46*Parameters!$B$6-IF($B46="Gather",Parameters!$B$17,0))) -> 0 | L46: =IF($K45<=0,0,MAX(0,IF($B46="Travel",Parameters!$B$13*7,IF($B46="Work",Parameters!$B$14,0))-(SUM(D45:J45)-SUM(D46:J46)))) -> 0 | M46: =IF(K46<=0,"RUN OVER","alive") -> RUN OVER
A47: 41 | B47: Work | C47: 3 | D47: =IF($K46<=0,D46,IF($B47="Travel",MAX(0,D46-Parameters!$B$13),IF(AND($B47="Work",$C47=1),MAX(0,D46-Parameters!$B$14),IF(AND($B47="Gather",$C47=1),MIN(Parameters!$B$10,D46+Parameters!$B$16),D46)))) -> 0 | E47: =IF($K46<=0,E46,IF($B47="Travel",MAX(0,E46-Parameters!$B$13),IF(AND($B47="Work",$C47=2),MAX(0,E46-Parameters!$B$14),IF(AND($B47="Gather",$C47=2),MIN(Parameters!$B$10,E46+Parameters!$B$16),E46)))) -> 0 | F47: =IF($K46<=0,F46,IF($B47="Travel",MAX(0,F46-Parameters!$B$13),IF(AND($B47="Work",$C47=3),MAX(0,F46-Parameters!$B$14),IF(AND($B47="Gather",$C47=3),MIN(Parameters!$B$10,F46+Parameters!$B$16),F46)))) -> 40 | G47: =IF($K46<=0,G46,IF($B47="Travel",MAX(0,G46-Parameters!$B$13),IF(AND($B47="Work",$C47=4),MAX(0,G46-Parameters!$B$14),IF(AND($B47="Gather",$C47=4),MIN(Parameters!$B$10,G46+Parameters!$B$16),G46)))) -> 40 | H47: =IF($K46<=0,H46,IF($B47="Travel",MAX(0,H46-Parameters!$B$13),IF(AND($B47="Work",$C47=5),MAX(0,H46-Parameters!$B$14),IF(AND($B47="Gather",$C47=5),MIN(Parameters!$B$10,H46+Parameters!$B$16),H46)))) -> 40 | I47: =IF($K46<=0,I46,IF($B47="Travel",MAX(0,I46-Parameters!$B$13),IF(AND($B47="Work",$C47=6),MAX(0,I46-Parameters!$B$14),IF(AND($B47="Gather",$C47=6),MIN(Parameters!$B$10,I46+Parameters!$B$16),I46)))) -> 40 | J47: =IF($K46<=0,J46,IF($B47="Travel",MAX(0,J46-Parameters!$B$13),IF(AND($B47="Work",$C47=7),MAX(0,J46-Parameters!$B$14),IF(AND($B47="Gather",$C47=7),MIN(Parameters!$B$10,J46+Parameters!$B$16),J46)))) -> 0 | K47: =IF($K46<=0,0,MAX(0,K46-L47*Parameters!$B$6-IF($B47="Gather",Parameters!$B$17,0))) -> 0 | L47: =IF($K46<=0,0,MAX(0,IF($B47="Travel",Parameters!$B$13*7,IF($B47="Work",Parameters!$B$14,0))-(SUM(D46:J46)-SUM(D47:J47)))) -> 0 | M47: =IF(K47<=0,"RUN OVER","alive") -> RUN OVER
A48: 42 | B48: Work | C48: 3 | D48: =IF($K47<=0,D47,IF($B48="Travel",MAX(0,D47-Parameters!$B$13),IF(AND($B48="Work",$C48=1),MAX(0,D47-Parameters!$B$14),IF(AND($B48="Gather",$C48=1),MIN(Parameters!$B$10,D47+Parameters!$B$16),D47)))) -> 0 | E48: =IF($K47<=0,E47,IF($B48="Travel",MAX(0,E47-Parameters!$B$13),IF(AND($B48="Work",$C48=2),MAX(0,E47-Parameters!$B$14),IF(AND($B48="Gather",$C48=2),MIN(Parameters!$B$10,E47+Parameters!$B$16),E47)))) -> 0 | F48: =IF($K47<=0,F47,IF($B48="Travel",MAX(0,F47-Parameters!$B$13),IF(AND($B48="Work",$C48=3),MAX(0,F47-Parameters!$B$14),IF(AND($B48="Gather",$C48=3),MIN(Parameters!$B$10,F47+Parameters!$B$16),F47)))) -> 40 | G48: =IF($K47<=0,G47,IF($B48="Travel",MAX(0,G47-Parameters!$B$13),IF(AND($B48="Work",$C48=4),MAX(0,G47-Parameters!$B$14),IF(AND($B48="Gather",$C48=4),MIN(Parameters!$B$10,G47+Parameters!$B$16),G47)))) -> 40 | H48: =IF($K47<=0,H47,IF($B48="Travel",MAX(0,H47-Parameters!$B$13),IF(AND($B48="Work",$C48=5),MAX(0,H47-Parameters!$B$14),IF(AND($B48="Gather",$C48=5),MIN(Parameters!$B$10,H47+Parameters!$B$16),H47)))) -> 40 | I48: =IF($K47<=0,I47,IF($B48="Travel",MAX(0,I47-Parameters!$B$13),IF(AND($B48="Work",$C48=6),MAX(0,I47-Parameters!$B$14),IF(AND($B48="Gather",$C48=6),MIN(Parameters!$B$10,I47+Parameters!$B$16),I47)))) -> 40 | J48: =IF($K47<=0,J47,IF($B48="Travel",MAX(0,J47-Parameters!$B$13),IF(AND($B48="Work",$C48=7),MAX(0,J47-Parameters!$B$14),IF(AND($B48="Gather",$C48=7),MIN(Parameters!$B$10,J47+Parameters!$B$16),J47)))) -> 0 | K48: =IF($K47<=0,0,MAX(0,K47-L48*Parameters!$B$6-IF($B48="Gather",Parameters!$B$17,0))) -> 0 | L48: =IF($K47<=0,0,MAX(0,IF($B48="Travel",Parameters!$B$13*7,IF($B48="Work",Parameters!$B$14,0))-(SUM(D47:J47)-SUM(D48:J48)))) -> 0 | M48: =IF(K48<=0,"RUN OVER","alive") -> RUN OVER
A49: 43 | B49: Work | C49: 1 | D49: =IF($K48<=0,D48,IF($B49="Travel",MAX(0,D48-Parameters!$B$13),IF(AND($B49="Work",$C49=1),MAX(0,D48-Parameters!$B$14),IF(AND($B49="Gather",$C49=1),MIN(Parameters!$B$10,D48+Parameters!$B$16),D48)))) -> 0 | E49: =IF($K48<=0,E48,IF($B49="Travel",MAX(0,E48-Parameters!$B$13),IF(AND($B49="Work",$C49=2),MAX(0,E48-Parameters!$B$14),IF(AND($B49="Gather",$C49=2),MIN(Parameters!$B$10,E48+Parameters!$B$16),E48)))) -> 0 | F49: =IF($K48<=0,F48,IF($B49="Travel",MAX(0,F48-Parameters!$B$13),IF(AND($B49="Work",$C49=3),MAX(0,F48-Parameters!$B$14),IF(AND($B49="Gather",$C49=3),MIN(Parameters!$B$10,F48+Parameters!$B$16),F48)))) -> 40 | G49: =IF($K48<=0,G48,IF($B49="Travel",MAX(0,G48-Parameters!$B$13),IF(AND($B49="Work",$C49=4),MAX(0,G48-Parameters!$B$14),IF(AND($B49="Gather",$C49=4),MIN(Parameters!$B$10,G48+Parameters!$B$16),G48)))) -> 40 | H49: =IF($K48<=0,H48,IF($B49="Travel",MAX(0,H48-Parameters!$B$13),IF(AND($B49="Work",$C49=5),MAX(0,H48-Parameters!$B$14),IF(AND($B49="Gather",$C49=5),MIN(Parameters!$B$10,H48+Parameters!$B$16),H48)))) -> 40 | I49: =IF($K48<=0,I48,IF($B49="Travel",MAX(0,I48-Parameters!$B$13),IF(AND($B49="Work",$C49=6),MAX(0,I48-Parameters!$B$14),IF(AND($B49="Gather",$C49=6),MIN(Parameters!$B$10,I48+Parameters!$B$16),I48)))) -> 40 | J49: =IF($K48<=0,J48,IF($B49="Travel",MAX(0,J48-Parameters!$B$13),IF(AND($B49="Work",$C49=7),MAX(0,J48-Parameters!$B$14),IF(AND($B49="Gather",$C49=7),MIN(Parameters!$B$10,J48+Parameters!$B$16),J48)))) -> 0 | K49: =IF($K48<=0,0,MAX(0,K48-L49*Parameters!$B$6-IF($B49="Gather",Parameters!$B$17,0))) -> 0 | L49: =IF($K48<=0,0,MAX(0,IF($B49="Travel",Parameters!$B$13*7,IF($B49="Work",Parameters!$B$14,0))-(SUM(D48:J48)-SUM(D49:J49)))) -> 0 | M49: =IF(K49<=0,"RUN OVER","alive") -> RUN OVER
A50: 44 | B50: Work | C50: 1 | D50: =IF($K49<=0,D49,IF($B50="Travel",MAX(0,D49-Parameters!$B$13),IF(AND($B50="Work",$C50=1),MAX(0,D49-Parameters!$B$14),IF(AND($B50="Gather",$C50=1),MIN(Parameters!$B$10,D49+Parameters!$B$16),D49)))) -> 0 | E50: =IF($K49<=0,E49,IF($B50="Travel",MAX(0,E49-Parameters!$B$13),IF(AND($B50="Work",$C50=2),MAX(0,E49-Parameters!$B$14),IF(AND($B50="Gather",$C50=2),MIN(Parameters!$B$10,E49+Parameters!$B$16),E49)))) -> 0 | F50: =IF($K49<=0,F49,IF($B50="Travel",MAX(0,F49-Parameters!$B$13),IF(AND($B50="Work",$C50=3),MAX(0,F49-Parameters!$B$14),IF(AND($B50="Gather",$C50=3),MIN(Parameters!$B$10,F49+Parameters!$B$16),F49)))) -> 40 | G50: =IF($K49<=0,G49,IF($B50="Travel",MAX(0,G49-Parameters!$B$13),IF(AND($B50="Work",$C50=4),MAX(0,G49-Parameters!$B$14),IF(AND($B50="Gather",$C50=4),MIN(Parameters!$B$10,G49+Parameters!$B$16),G49)))) -> 40 | H50: =IF($K49<=0,H49,IF($B50="Travel",MAX(0,H49-Parameters!$B$13),IF(AND($B50="Work",$C50=5),MAX(0,H49-Parameters!$B$14),IF(AND($B50="Gather",$C50=5),MIN(Parameters!$B$10,H49+Parameters!$B$16),H49)))) -> 40 | I50: =IF($K49<=0,I49,IF($B50="Travel",MAX(0,I49-Parameters!$B$13),IF(AND($B50="Work",$C50=6),MAX(0,I49-Parameters!$B$14),IF(AND($B50="Gather",$C50=6),MIN(Parameters!$B$10,I49+Parameters!$B$16),I49)))) -> 40 | J50: =IF($K49<=0,J49,IF($B50="Travel",MAX(0,J49-Parameters!$B$13),IF(AND($B50="Work",$C50=7),MAX(0,J49-Parameters!$B$14),IF(AND($B50="Gather",$C50=7),MIN(Parameters!$B$10,J49+Parameters!$B$16),J49)))) -> 0 | K50: =IF($K49<=0,0,MAX(0,K49-L50*Parameters!$B$6-IF($B50="Gather",Parameters!$B$17,0))) -> 0 | L50: =IF($K49<=0,0,MAX(0,IF($B50="Travel",Parameters!$B$13*7,IF($B50="Work",Parameters!$B$14,0))-(SUM(D49:J49)-SUM(D50:J50)))) -> 0 | M50: =IF(K50<=0,"RUN OVER","alive") -> RUN OVER
A51: 45 | B51: Work | C51: 1 | D51: =IF($K50<=0,D50,IF($B51="Travel",MAX(0,D50-Parameters!$B$13),IF(AND($B51="Work",$C51=1),MAX(0,D50-Parameters!$B$14),IF(AND($B51="Gather",$C51=1),MIN(Parameters!$B$10,D50+Parameters!$B$16),D50)))) -> 0 | E51: =IF($K50<=0,E50,IF($B51="Travel",MAX(0,E50-Parameters!$B$13),IF(AND($B51="Work",$C51=2),MAX(0,E50-Parameters!$B$14),IF(AND($B51="Gather",$C51=2),MIN(Parameters!$B$10,E50+Parameters!$B$16),E50)))) -> 0 | F51: =IF($K50<=0,F50,IF($B51="Travel",MAX(0,F50-Parameters!$B$13),IF(AND($B51="Work",$C51=3),MAX(0,F50-Parameters!$B$14),IF(AND($B51="Gather",$C51=3),MIN(Parameters!$B$10,F50+Parameters!$B$16),F50)))) -> 40 | G51: =IF($K50<=0,G50,IF($B51="Travel",MAX(0,G50-Parameters!$B$13),IF(AND($B51="Work",$C51=4),MAX(0,G50-Parameters!$B$14),IF(AND($B51="Gather",$C51=4),MIN(Parameters!$B$10,G50+Parameters!$B$16),G50)))) -> 40 | H51: =IF($K50<=0,H50,IF($B51="Travel",MAX(0,H50-Parameters!$B$13),IF(AND($B51="Work",$C51=5),MAX(0,H50-Parameters!$B$14),IF(AND($B51="Gather",$C51=5),MIN(Parameters!$B$10,H50+Parameters!$B$16),H50)))) -> 40 | I51: =IF($K50<=0,I50,IF($B51="Travel",MAX(0,I50-Parameters!$B$13),IF(AND($B51="Work",$C51=6),MAX(0,I50-Parameters!$B$14),IF(AND($B51="Gather",$C51=6),MIN(Parameters!$B$10,I50+Parameters!$B$16),I50)))) -> 40 | J51: =IF($K50<=0,J50,IF($B51="Travel",MAX(0,J50-Parameters!$B$13),IF(AND($B51="Work",$C51=7),MAX(0,J50-Parameters!$B$14),IF(AND($B51="Gather",$C51=7),MIN(Parameters!$B$10,J50+Parameters!$B$16),J50)))) -> 0 | K51: =IF($K50<=0,0,MAX(0,K50-L51*Parameters!$B$6-IF($B51="Gather",Parameters!$B$17,0))) -> 0 | L51: =IF($K50<=0,0,MAX(0,IF($B51="Travel",Parameters!$B$13*7,IF($B51="Work",Parameters!$B$14,0))-(SUM(D50:J50)-SUM(D51:J51)))) -> 0 | M51: =IF(K51<=0,"RUN OVER","alive") -> RUN OVER

Sheet Health Checks
A1: Health Checks
A2: Each row is a design question the numbers must answer. CHECK means a design problem.
A4: # | B4: Question | C4: Measure | D4: Value | E4: Wanted | F4: Verdict
A5: 1 | B5: Is a run long enough to be a puzzle? | C5: Actions completed in the ledger | D5: ='Run Ledger'!P6 -> 33 | E5: =Parameters!$B$21&" to "&Parameters!$B$22 -> 30 to 90 | F5: =IF(AND(D5>=Parameters!$B$21,D5<=Parameters!$B$22),"OK","CHECK") -> OK
A6: 2 | B6: Does Spike actually travel less than Balanced? | C6: Spike vitality on traversal 2 vs Balanced | D6: ='Build Comparison'!C16-'Build Comparison'!C15 -> 90 | E6: Spike costs more | F6: =IF(D6>0,"OK","CHECK") -> OK
A7: 3 | B7: Can Spike reach a magnitude wall? | C7: Spike strongest pool vs requirement | D7: ='Build Comparison'!B26 -> 640 | E7: =Parameters!$B$25 -> 400 | F7: =IF(D7>=Parameters!$B$25,"OK","CHECK") -> OK
A8: 4 | B8: Can Balanced reach a breadth wall? | C8: Balanced pools at or above the floor | D8: =COUNTIF('Build Comparison'!B6:H6,">="&Parameters!$B$26) -> 7 | E8: 4 or more | F8: =IF(D8>=4,"OK","CHECK") -> OK
A9: 5 | B9: Is Spike locked out of breadth walls? | C9: Spike pools at or above the floor | D9: =COUNTIF('Build Comparison'!B7:H7,">="&Parameters!$B$26) -> 1 | E9: fewer than 4 | F9: =IF(D9<4,"OK","CHECK") -> OK
A10: 6 | B10: Is Balanced locked out of magnitude walls? | C10: Balanced strongest pool vs requirement | D10: ='Build Comparison'!B25 -> 100 | E10: below =Parameters!$B$25 | F10: =IF(D10<Parameters!$B$25,"OK","CHECK") -> OK
A11: 7 | B11: Does travel dominate the cost structure? | C11: One traversal vs one working | D11: =Parameters!$B$13*7/Parameters!$B$14 -> 13.125 | E11: 5x or more | F11: =IF(D11>=5,"OK","CHECK") -> OK
A12: 8 | B12: Is Gather bounded? | C12: Vitality cost per gather | D12: =Parameters!$B$17 -> 2 | E12: above zero | F12: =IF(D12>0,"OK","CHECK") -> OK
A13: 9 | B13: Does the ledger run end at all? | C13: Vitality remaining at the last step | D13: ='Run Ledger'!K51 -> 0 | E13: zero | F13: =IF(D13<=0,"OK","CHECK") -> OK
B15: Checks failing | D15: =COUNTIF(F5:F13,"CHECK") -> 0 | E15: Each is a design decision, not a spreadsheet bug.
B18: WHAT EACH FAILURE MEANS
B19: 1 Run too short: lower travel cost or raise the pathos budget. Too long: the reverse.
B20: 2-6 If archetypes are not separated, the wall thresholds are wrong, not the builds.
B21: 7 If travel is cheap, every build tours and pool shape stops deciding route length.
B22: 8 Gather at zero vitality cost makes an infinite run. This is open question 9 in the GDD.
B23: 9 If the ledger never ends, the route is sustainable - which is the same problem as 8.
